<?xml version="1.0" encoding="UTF-8"?>
<!-- id=编号 require_points=需求积分 level_min=等级下限（闭区间） level_max=等级上限（闭区间） award1_type=奖励1类型 award1_value=奖励1类型值 award1_size=奖励1数量 award2_type=奖励2类型 award2_value=奖励2类型值 award2_size=奖励2数量 award3_type=奖励3类型 award3_value=奖励3类型值 award3_size=奖励3数量 award4_type=奖励4类型 award4_value=奖励4类型值 award4_size=奖励4数量 -->
<root>
    <data id="101" require_points="30" level_min="1" level_max="20" award1_type="1" award1_value="0" award1_size="20000" award2_type="2" award2_value="0" award2_size="20" award3_type="0" award3_value="0" award3_size="0" award4_type="0" award4_value="0" award4_size="0" />
    <data id="102" require_points="60" level_min="1" level_max="20" award1_type="1" award1_value="0" award1_size="40000" award2_type="2" award2_value="0" award2_size="30" award3_type="0" award3_value="0" award3_size="0" award4_type="0" award4_value="0" award4_size="0" />
    <data id="103" require_points="90" level_min="1" level_max="20" award1_type="3" award1_value="37" award1_size="1" award2_type="2" award2_value="0" award2_size="50" award3_type="0" award3_value="0" award3_size="0" award4_type="0" award4_value="0" award4_size="0" />
    <data id="104" require_points="120" level_min="1" level_max="20" award1_type="3" award1_value="37" award1_size="1" award2_type="2" award2_value="0" award2_size="100" award3_type="0" award3_value="0" award3_size="0" award4_type="0" award4_value="0" award4_size="0" />
    <data id="201" require_points="30" level_min="21" level_max="34" award1_type="1" award1_value="0" award1_size="25000" award2_type="2" award2_value="0" award2_size="20" award3_type="0" award3_value="0" award3_size="0" award4_type="0" award4_value="0" award4_size="0" />
    <data id="202" require_points="60" level_min="21" level_max="34" award1_type="1" award1_value="0" award1_size="50000" award2_type="2" award2_value="0" award2_size="30" award3_type="3" award3_value="15" award3_size="1" award4_type="0" award4_value="0" award4_size="0" />
    <data id="203" require_points="90" level_min="21" level_max="34" award1_type="3" award1_value="37" award1_size="1" award2_type="2" award2_value="0" award2_size="50" award3_type="3" award3_value="15" award3_size="2" award4_type="0" award4_value="0" award4_size="0" />
    <data id="204" require_points="120" level_min="21" level_max="34" award1_type="3" award1_value="37" award1_size="1" award2_type="2" award2_value="0" award2_size="100" award3_type="3" award3_value="15" award3_size="3" award4_type="0" award4_value="0" award4_size="0" />
    <data id="301" require_points="30" level_min="35" level_max="50" award1_type="1" award1_value="0" award1_size="30000" award2_type="2" award2_value="0" award2_size="20" award3_type="0" award3_value="0" award3_size="0" award4_type="0" award4_value="0" award4_size="0" />
    <data id="302" require_points="60" level_min="35" level_max="50" award1_type="1" award1_value="0" award1_size="60000" award2_type="2" award2_value="0" award2_size="30" award3_type="3" award3_value="15" award3_size="1" award4_type="0" award4_value="0" award4_size="0" />
    <data id="303" require_points="90" level_min="35" level_max="50" award1_type="3" award1_value="37" award1_size="1" award2_type="2" award2_value="0" award2_size="50" award3_type="3" award3_value="15" award3_size="2" award4_type="3" award4_value="5" award4_size="1" />
    <data id="304" require_points="120" level_min="35" level_max="50" award1_type="3" award1_value="37" award1_size="1" award2_type="2" award2_value="0" award2_size="100" award3_type="3" award3_value="15" award3_size="3" award4_type="3" award4_value="5" award4_size="1" />
    <data id="401" require_points="30" level_min="51" level_max="60" award1_type="1" award1_value="0" award1_size="40000" award2_type="2" award2_value="0" award2_size="20" award3_type="3" award3_value="5" award3_size="1" award4_type="0" award4_value="0" award4_size="0" />
    <data id="402" require_points="60" level_min="51" level_max="60" award1_type="1" award1_value="0" award1_size="70000" award2_type="2" award2_value="0" award2_size="30" award3_type="3" award3_value="15" award3_size="1" award4_type="3" award4_value="5" award4_size="1" />
    <data id="403" require_points="90" level_min="51" level_max="60" award1_type="3" award1_value="37" award1_size="1" award2_type="2" award2_value="0" award2_size="50" award3_type="3" award3_value="15" award3_size="2" award4_type="3" award4_value="5" award4_size="2" />
    <data id="404" require_points="120" level_min="51" level_max="60" award1_type="3" award1_value="37" award1_size="1" award2_type="2" award2_value="0" award2_size="100" award3_type="3" award3_value="15" award3_size="3" award4_type="3" award4_value="5" award4_size="2" />
    <data id="501" require_points="30" level_min="61" level_max="70" award1_type="1" award1_value="0" award1_size="50000" award2_type="2" award2_value="0" award2_size="20" award3_type="3" award3_value="5" award3_size="1" award4_type="0" award4_value="0" award4_size="0" />
    <data id="502" require_points="60" level_min="61" level_max="70" award1_type="1" award1_value="0" award1_size="80000" award2_type="2" award2_value="0" award2_size="30" award3_type="3" award3_value="15" award3_size="1" award4_type="3" award4_value="5" award4_size="1" />
    <data id="503" require_points="90" level_min="61" level_max="70" award1_type="3" award1_value="37" award1_size="1" award2_type="2" award2_value="0" award2_size="50" award3_type="3" award3_value="15" award3_size="2" award4_type="3" award4_value="5" award4_size="2" />
    <data id="504" require_points="120" level_min="61" level_max="70" award1_type="3" award1_value="37" award1_size="1" award2_type="2" award2_value="0" award2_size="100" award3_type="3" award3_value="15" award3_size="3" award4_type="3" award4_value="5" award4_size="2" />
    <data id="601" require_points="30" level_min="71" level_max="80" award1_type="1" award1_value="0" award1_size="60000" award2_type="2" award2_value="0" award2_size="20" award3_type="3" award3_value="5" award3_size="1" award4_type="0" award4_value="0" award4_size="0" />
    <data id="602" require_points="60" level_min="71" level_max="80" award1_type="1" award1_value="0" award1_size="90000" award2_type="2" award2_value="0" award2_size="30" award3_type="3" award3_value="15" award3_size="1" award4_type="3" award4_value="5" award4_size="1" />
    <data id="603" require_points="90" level_min="71" level_max="80" award1_type="3" award1_value="37" award1_size="1" award2_type="2" award2_value="0" award2_size="50" award3_type="3" award3_value="15" award3_size="2" award4_type="3" award4_value="5" award4_size="2" />
    <data id="604" require_points="120" level_min="71" level_max="80" award1_type="3" award1_value="37" award1_size="1" award2_type="2" award2_value="0" award2_size="100" award3_type="3" award3_value="15" award3_size="3" award4_type="3" award4_value="5" award4_size="2" />
    <data id="701" require_points="30" level_min="81" level_max="100" award1_type="1" award1_value="0" award1_size="60000" award2_type="2" award2_value="0" award2_size="20" award3_type="3" award3_value="5" award3_size="1" award4_type="0" award4_value="0" award4_size="0" />
    <data id="702" require_points="60" level_min="81" level_max="100" award1_type="1" award1_value="0" award1_size="90000" award2_type="2" award2_value="0" award2_size="30" award3_type="3" award3_value="15" award3_size="1" award4_type="3" award4_value="5" award4_size="1" />
    <data id="703" require_points="90" level_min="81" level_max="100" award1_type="3" award1_value="37" award1_size="1" award2_type="2" award2_value="0" award2_size="50" award3_type="3" award3_value="15" award3_size="2" award4_type="3" award4_value="5" award4_size="2" />
    <data id="704" require_points="120" level_min="81" level_max="100" award1_type="3" award1_value="37" award1_size="1" award2_type="2" award2_value="0" award2_size="100" award3_type="3" award3_value="15" award3_size="3" award4_type="3" award4_value="5" award4_size="2" />
    <data id="801" require_points="30" level_min="101" level_max="120" award1_type="1" award1_value="0" award1_size="60000" award2_type="2" award2_value="0" award2_size="20" award3_type="3" award3_value="5" award3_size="1" award4_type="0" award4_value="0" award4_size="0" />
    <data id="802" require_points="60" level_min="101" level_max="120" award1_type="1" award1_value="0" award1_size="90000" award2_type="2" award2_value="0" award2_size="30" award3_type="3" award3_value="15" award3_size="1" award4_type="3" award4_value="5" award4_size="1" />
    <data id="803" require_points="90" level_min="101" level_max="120" award1_type="3" award1_value="37" award1_size="1" award2_type="2" award2_value="0" award2_size="50" award3_type="3" award3_value="15" award3_size="2" award4_type="3" award4_value="5" award4_size="2" />
    <data id="804" require_points="120" level_min="101" level_max="120" award1_type="3" award1_value="37" award1_size="1" award2_type="2" award2_value="0" award2_size="100" award3_type="3" award3_value="15" award3_size="3" award4_type="3" award4_value="5" award4_size="2" />
    <data id="901" require_points="30" level_min="121" level_max="140" award1_type="1" award1_value="0" award1_size="90000" award2_type="2" award2_value="0" award2_size="20" award3_type="3" award3_value="5" award3_size="1" award4_type="0" award4_value="0" award4_size="0" />
    <data id="902" require_points="60" level_min="121" level_max="140" award1_type="1" award1_value="0" award1_size="135000" award2_type="2" award2_value="0" award2_size="30" award3_type="3" award3_value="15" award3_size="1" award4_type="3" award4_value="5" award4_size="1" />
    <data id="903" require_points="90" level_min="121" level_max="140" award1_type="3" award1_value="37" award1_size="2" award2_type="2" award2_value="0" award2_size="50" award3_type="3" award3_value="15" award3_size="2" award4_type="3" award4_value="5" award4_size="2" />
    <data id="904" require_points="120" level_min="121" level_max="140" award1_type="3" award1_value="37" award1_size="2" award2_type="2" award2_value="0" award2_size="100" award3_type="3" award3_value="15" award3_size="3" award4_type="3" award4_value="5" award4_size="2" />
    <data id="1001" require_points="30" level_min="141" level_max="999" award1_type="1" award1_value="0" award1_size="135000" award2_type="2" award2_value="0" award2_size="20" award3_type="3" award3_value="5" award3_size="1" award4_type="0" award4_value="0" award4_size="0" />
    <data id="1002" require_points="60" level_min="141" level_max="999" award1_type="1" award1_value="0" award1_size="205000" award2_type="2" award2_value="0" award2_size="30" award3_type="3" award3_value="15" award3_size="1" award4_type="3" award4_value="5" award4_size="1" />
    <data id="1003" require_points="90" level_min="141" level_max="999" award1_type="3" award1_value="37" award1_size="2" award2_type="2" award2_value="0" award2_size="50" award3_type="3" award3_value="15" award3_size="2" award4_type="3" award4_value="5" award4_size="2" />
    <data id="1004" require_points="120" level_min="141" level_max="999" award1_type="3" award1_value="37" award1_size="2" award2_type="2" award2_value="0" award2_size="100" award3_type="3" award3_value="15" award3_size="3" award4_type="3" award4_value="5" award4_size="2" />
</root>