<?xml version="1.0" encoding="UTF-8"?>
<!-- id=编号 level_min=玩家最小等级 level_max=玩家最大等级 vip_level_min=可购买VIP最小等级 vip_level_max=可购买VIP最大等级 bag_1_cost_type=礼包消耗类型 bag_1_cost_value=礼包消耗类型值 bag_1_cost_time=礼包可购买次数 bag_1_item_1_type=礼包物品1类型 bag_1_item_1_value=礼包物品1类型值 bag_1_item_1_size=礼包物品1数量 bag_1_item_2_type=礼包物品2类型 bag_1_item_2_value=礼包物品2类型值 bag_1_item_2_size=礼包物品2数量 bag_1_item_3_type=礼包物品3类型 bag_1_item_3_value=礼包物品3类型值 bag_1_item_3_size=礼包物品3数量 bag_1_item_4_type=礼包物品4类型 bag_1_item_4_value=礼包物品4类型值 bag_1_item_4_size=礼包物品4数量 -->
<root>
    <data id="10010101" level_min="25" level_max="49" vip_level_min="0" vip_level_max="5" bag_1_cost_type="2" bag_1_cost_value="250" bag_1_cost_time="1" bag_1_item_1_type="3" bag_1_item_1_value="5" bag_1_item_1_size="10" bag_1_item_2_type="3" bag_1_item_2_value="4" bag_1_item_2_size="10" bag_1_item_3_type="0" bag_1_item_3_value="0" bag_1_item_3_size="0" bag_1_item_4_type="0" bag_1_item_4_value="0" bag_1_item_4_size="0" />
    <data id="10010102" level_min="25" level_max="49" vip_level_min="0" vip_level_max="5" bag_1_cost_type="2" bag_1_cost_value="175" bag_1_cost_time="1" bag_1_item_1_type="1" bag_1_item_1_value="0" bag_1_item_1_size="500000" bag_1_item_2_type="0" bag_1_item_2_value="0" bag_1_item_2_size="0" bag_1_item_3_type="0" bag_1_item_3_value="0" bag_1_item_3_size="0" bag_1_item_4_type="0" bag_1_item_4_value="0" bag_1_item_4_size="0" />
    <data id="10010103" level_min="25" level_max="49" vip_level_min="0" vip_level_max="5" bag_1_cost_type="2" bag_1_cost_value="580" bag_1_cost_time="1" bag_1_item_1_type="3" bag_1_item_1_value="21" bag_1_item_1_size="5" bag_1_item_2_type="3" bag_1_item_2_value="13" bag_1_item_2_size="50" bag_1_item_3_type="0" bag_1_item_3_value="0" bag_1_item_3_size="0" bag_1_item_4_type="0" bag_1_item_4_value="0" bag_1_item_4_size="0" />
    <data id="10010201" level_min="25" level_max="49" vip_level_min="6" vip_level_max="8" bag_1_cost_type="2" bag_1_cost_value="250" bag_1_cost_time="1" bag_1_item_1_type="3" bag_1_item_1_value="5" bag_1_item_1_size="10" bag_1_item_2_type="3" bag_1_item_2_value="4" bag_1_item_2_size="10" bag_1_item_3_type="0" bag_1_item_3_value="0" bag_1_item_3_size="0" bag_1_item_4_type="0" bag_1_item_4_value="0" bag_1_item_4_size="0" />
    <data id="10010202" level_min="25" level_max="49" vip_level_min="6" vip_level_max="8" bag_1_cost_type="2" bag_1_cost_value="280" bag_1_cost_time="1" bag_1_item_1_type="1" bag_1_item_1_value="0" bag_1_item_1_size="800000" bag_1_item_2_type="0" bag_1_item_2_value="0" bag_1_item_2_size="0" bag_1_item_3_type="0" bag_1_item_3_value="0" bag_1_item_3_size="0" bag_1_item_4_type="0" bag_1_item_4_value="0" bag_1_item_4_size="0" />
    <data id="10010203" level_min="25" level_max="49" vip_level_min="6" vip_level_max="8" bag_1_cost_type="2" bag_1_cost_value="580" bag_1_cost_time="2" bag_1_item_1_type="3" bag_1_item_1_value="21" bag_1_item_1_size="5" bag_1_item_2_type="3" bag_1_item_2_value="13" bag_1_item_2_size="50" bag_1_item_3_type="0" bag_1_item_3_value="0" bag_1_item_3_size="0" bag_1_item_4_type="0" bag_1_item_4_value="0" bag_1_item_4_size="0" />
    <data id="10010204" level_min="25" level_max="49" vip_level_min="6" vip_level_max="8" bag_1_cost_type="2" bag_1_cost_value="1250" bag_1_cost_time="1" bag_1_item_1_type="3" bag_1_item_1_value="188" bag_1_item_1_size="2" bag_1_item_2_type="3" bag_1_item_2_value="18" bag_1_item_2_size="500" bag_1_item_3_type="0" bag_1_item_3_value="0" bag_1_item_3_size="0" bag_1_item_4_type="0" bag_1_item_4_value="0" bag_1_item_4_size="0" />
    <data id="10010301" level_min="25" level_max="49" vip_level_min="9" vip_level_max="12" bag_1_cost_type="2" bag_1_cost_value="250" bag_1_cost_time="1" bag_1_item_1_type="3" bag_1_item_1_value="5" bag_1_item_1_size="10" bag_1_item_2_type="3" bag_1_item_2_value="4" bag_1_item_2_size="10" bag_1_item_3_type="0" bag_1_item_3_value="0" bag_1_item_3_size="0" bag_1_item_4_type="0" bag_1_item_4_value="0" bag_1_item_4_size="0" />
    <data id="10010302" level_min="25" level_max="49" vip_level_min="9" vip_level_max="12" bag_1_cost_type="2" bag_1_cost_value="350" bag_1_cost_time="1" bag_1_item_1_type="1" bag_1_item_1_value="0" bag_1_item_1_size="1000000" bag_1_item_2_type="0" bag_1_item_2_value="0" bag_1_item_2_size="0" bag_1_item_3_type="0" bag_1_item_3_value="0" bag_1_item_3_size="0" bag_1_item_4_type="0" bag_1_item_4_value="0" bag_1_item_4_size="0" />
    <data id="10010303" level_min="25" level_max="49" vip_level_min="9" vip_level_max="12" bag_1_cost_type="2" bag_1_cost_value="580" bag_1_cost_time="3" bag_1_item_1_type="3" bag_1_item_1_value="21" bag_1_item_1_size="5" bag_1_item_2_type="3" bag_1_item_2_value="13" bag_1_item_2_size="50" bag_1_item_3_type="0" bag_1_item_3_value="0" bag_1_item_3_size="0" bag_1_item_4_type="0" bag_1_item_4_value="0" bag_1_item_4_size="0" />
    <data id="10010304" level_min="25" level_max="49" vip_level_min="9" vip_level_max="12" bag_1_cost_type="2" bag_1_cost_value="1250" bag_1_cost_time="2" bag_1_item_1_type="3" bag_1_item_1_value="188" bag_1_item_1_size="2" bag_1_item_2_type="3" bag_1_item_2_value="18" bag_1_item_2_size="500" bag_1_item_3_type="0" bag_1_item_3_value="0" bag_1_item_3_size="0" bag_1_item_4_type="0" bag_1_item_4_value="0" bag_1_item_4_size="0" />
    <data id="10020101" level_min="50" level_max="69" vip_level_min="0" vip_level_max="5" bag_1_cost_type="2" bag_1_cost_value="250" bag_1_cost_time="1" bag_1_item_1_type="3" bag_1_item_1_value="5" bag_1_item_1_size="10" bag_1_item_2_type="3" bag_1_item_2_value="4" bag_1_item_2_size="10" bag_1_item_3_type="0" bag_1_item_3_value="0" bag_1_item_3_size="0" bag_1_item_4_type="0" bag_1_item_4_value="0" bag_1_item_4_size="0" />
    <data id="10020102" level_min="50" level_max="69" vip_level_min="0" vip_level_max="5" bag_1_cost_type="2" bag_1_cost_value="175" bag_1_cost_time="1" bag_1_item_1_type="1" bag_1_item_1_value="0" bag_1_item_1_size="500000" bag_1_item_2_type="0" bag_1_item_2_value="0" bag_1_item_2_size="0" bag_1_item_3_type="0" bag_1_item_3_value="0" bag_1_item_3_size="0" bag_1_item_4_type="0" bag_1_item_4_value="0" bag_1_item_4_size="0" />
    <data id="10020103" level_min="50" level_max="69" vip_level_min="0" vip_level_max="5" bag_1_cost_type="2" bag_1_cost_value="580" bag_1_cost_time="1" bag_1_item_1_type="3" bag_1_item_1_value="21" bag_1_item_1_size="5" bag_1_item_2_type="3" bag_1_item_2_value="13" bag_1_item_2_size="50" bag_1_item_3_type="0" bag_1_item_3_value="0" bag_1_item_3_size="0" bag_1_item_4_type="0" bag_1_item_4_value="0" bag_1_item_4_size="0" />
    <data id="10020104" level_min="50" level_max="69" vip_level_min="0" vip_level_max="5" bag_1_cost_type="2" bag_1_cost_value="950" bag_1_cost_time="1" bag_1_item_1_type="23" bag_1_item_1_value="0" bag_1_item_1_size="500" bag_1_item_2_type="3" bag_1_item_2_value="60" bag_1_item_2_size="500" bag_1_item_3_type="3" bag_1_item_3_value="73" bag_1_item_3_size="5" bag_1_item_4_type="0" bag_1_item_4_value="0" bag_1_item_4_size="0" />
    <data id="10020105" level_min="50" level_max="69" vip_level_min="0" vip_level_max="5" bag_1_cost_type="2" bag_1_cost_value="1250" bag_1_cost_time="1" bag_1_item_1_type="3" bag_1_item_1_value="188" bag_1_item_1_size="2" bag_1_item_2_type="3" bag_1_item_2_value="18" bag_1_item_2_size="500" bag_1_item_3_type="0" bag_1_item_3_value="0" bag_1_item_3_size="0" bag_1_item_4_type="0" bag_1_item_4_value="0" bag_1_item_4_size="0" />
    <data id="10020201" level_min="50" level_max="69" vip_level_min="6" vip_level_max="8" bag_1_cost_type="2" bag_1_cost_value="250" bag_1_cost_time="1" bag_1_item_1_type="3" bag_1_item_1_value="5" bag_1_item_1_size="10" bag_1_item_2_type="3" bag_1_item_2_value="4" bag_1_item_2_size="10" bag_1_item_3_type="0" bag_1_item_3_value="0" bag_1_item_3_size="0" bag_1_item_4_type="0" bag_1_item_4_value="0" bag_1_item_4_size="0" />
    <data id="10020202" level_min="50" level_max="69" vip_level_min="6" vip_level_max="8" bag_1_cost_type="2" bag_1_cost_value="280" bag_1_cost_time="1" bag_1_item_1_type="1" bag_1_item_1_value="0" bag_1_item_1_size="800000" bag_1_item_2_type="0" bag_1_item_2_value="0" bag_1_item_2_size="0" bag_1_item_3_type="0" bag_1_item_3_value="0" bag_1_item_3_size="0" bag_1_item_4_type="0" bag_1_item_4_value="0" bag_1_item_4_size="0" />
    <data id="10020203" level_min="50" level_max="69" vip_level_min="6" vip_level_max="8" bag_1_cost_type="2" bag_1_cost_value="580" bag_1_cost_time="2" bag_1_item_1_type="3" bag_1_item_1_value="21" bag_1_item_1_size="5" bag_1_item_2_type="3" bag_1_item_2_value="13" bag_1_item_2_size="50" bag_1_item_3_type="0" bag_1_item_3_value="0" bag_1_item_3_size="0" bag_1_item_4_type="0" bag_1_item_4_value="0" bag_1_item_4_size="0" />
    <data id="10020204" level_min="50" level_max="69" vip_level_min="6" vip_level_max="8" bag_1_cost_type="2" bag_1_cost_value="950" bag_1_cost_time="2" bag_1_item_1_type="23" bag_1_item_1_value="0" bag_1_item_1_size="500" bag_1_item_2_type="3" bag_1_item_2_value="60" bag_1_item_2_size="500" bag_1_item_3_type="3" bag_1_item_3_value="73" bag_1_item_3_size="5" bag_1_item_4_type="0" bag_1_item_4_value="0" bag_1_item_4_size="0" />
    <data id="10020205" level_min="50" level_max="69" vip_level_min="6" vip_level_max="8" bag_1_cost_type="2" bag_1_cost_value="1250" bag_1_cost_time="2" bag_1_item_1_type="3" bag_1_item_1_value="188" bag_1_item_1_size="2" bag_1_item_2_type="3" bag_1_item_2_value="18" bag_1_item_2_size="500" bag_1_item_3_type="0" bag_1_item_3_value="0" bag_1_item_3_size="0" bag_1_item_4_type="0" bag_1_item_4_value="0" bag_1_item_4_size="0" />
    <data id="10020301" level_min="50" level_max="69" vip_level_min="9" vip_level_max="12" bag_1_cost_type="2" bag_1_cost_value="250" bag_1_cost_time="1" bag_1_item_1_type="3" bag_1_item_1_value="5" bag_1_item_1_size="10" bag_1_item_2_type="3" bag_1_item_2_value="4" bag_1_item_2_size="10" bag_1_item_3_type="0" bag_1_item_3_value="0" bag_1_item_3_size="0" bag_1_item_4_type="0" bag_1_item_4_value="0" bag_1_item_4_size="0" />
    <data id="10020302" level_min="50" level_max="69" vip_level_min="9" vip_level_max="12" bag_1_cost_type="2" bag_1_cost_value="350" bag_1_cost_time="1" bag_1_item_1_type="1" bag_1_item_1_value="0" bag_1_item_1_size="1000000" bag_1_item_2_type="0" bag_1_item_2_value="0" bag_1_item_2_size="0" bag_1_item_3_type="0" bag_1_item_3_value="0" bag_1_item_3_size="0" bag_1_item_4_type="0" bag_1_item_4_value="0" bag_1_item_4_size="0" />
    <data id="10020303" level_min="50" level_max="69" vip_level_min="9" vip_level_max="12" bag_1_cost_type="2" bag_1_cost_value="580" bag_1_cost_time="3" bag_1_item_1_type="3" bag_1_item_1_value="21" bag_1_item_1_size="5" bag_1_item_2_type="3" bag_1_item_2_value="13" bag_1_item_2_size="50" bag_1_item_3_type="0" bag_1_item_3_value="0" bag_1_item_3_size="0" bag_1_item_4_type="0" bag_1_item_4_value="0" bag_1_item_4_size="0" />
    <data id="10020304" level_min="50" level_max="69" vip_level_min="9" vip_level_max="12" bag_1_cost_type="2" bag_1_cost_value="950" bag_1_cost_time="3" bag_1_item_1_type="23" bag_1_item_1_value="0" bag_1_item_1_size="500" bag_1_item_2_type="3" bag_1_item_2_value="60" bag_1_item_2_size="500" bag_1_item_3_type="3" bag_1_item_3_value="73" bag_1_item_3_size="5" bag_1_item_4_type="0" bag_1_item_4_value="0" bag_1_item_4_size="0" />
    <data id="10020305" level_min="50" level_max="69" vip_level_min="9" vip_level_max="12" bag_1_cost_type="2" bag_1_cost_value="1250" bag_1_cost_time="3" bag_1_item_1_type="3" bag_1_item_1_value="188" bag_1_item_1_size="2" bag_1_item_2_type="3" bag_1_item_2_value="18" bag_1_item_2_size="500" bag_1_item_3_type="0" bag_1_item_3_value="0" bag_1_item_3_size="0" bag_1_item_4_type="0" bag_1_item_4_value="0" bag_1_item_4_size="0" />
    <data id="10030101" level_min="70" level_max="79" vip_level_min="0" vip_level_max="5" bag_1_cost_type="2" bag_1_cost_value="250" bag_1_cost_time="1" bag_1_item_1_type="3" bag_1_item_1_value="5" bag_1_item_1_size="10" bag_1_item_2_type="3" bag_1_item_2_value="4" bag_1_item_2_size="10" bag_1_item_3_type="0" bag_1_item_3_value="0" bag_1_item_3_size="0" bag_1_item_4_type="0" bag_1_item_4_value="0" bag_1_item_4_size="0" />
    <data id="10030102" level_min="70" level_max="79" vip_level_min="0" vip_level_max="5" bag_1_cost_type="2" bag_1_cost_value="175" bag_1_cost_time="2" bag_1_item_1_type="1" bag_1_item_1_value="0" bag_1_item_1_size="500000" bag_1_item_2_type="0" bag_1_item_2_value="0" bag_1_item_2_size="0" bag_1_item_3_type="0" bag_1_item_3_value="0" bag_1_item_3_size="0" bag_1_item_4_type="0" bag_1_item_4_value="0" bag_1_item_4_size="0" />
    <data id="10030103" level_min="70" level_max="79" vip_level_min="0" vip_level_max="5" bag_1_cost_type="2" bag_1_cost_value="580" bag_1_cost_time="1" bag_1_item_1_type="3" bag_1_item_1_value="21" bag_1_item_1_size="5" bag_1_item_2_type="3" bag_1_item_2_value="13" bag_1_item_2_size="50" bag_1_item_3_type="0" bag_1_item_3_value="0" bag_1_item_3_size="0" bag_1_item_4_type="0" bag_1_item_4_value="0" bag_1_item_4_size="0" />
    <data id="10030104" level_min="70" level_max="79" vip_level_min="0" vip_level_max="5" bag_1_cost_type="2" bag_1_cost_value="1100" bag_1_cost_time="1" bag_1_item_1_type="23" bag_1_item_1_value="0" bag_1_item_1_size="500" bag_1_item_2_type="3" bag_1_item_2_value="60" bag_1_item_2_size="500" bag_1_item_3_type="3" bag_1_item_3_value="74" bag_1_item_3_size="2" bag_1_item_4_type="0" bag_1_item_4_value="0" bag_1_item_4_size="0" />
    <data id="10030105" level_min="70" level_max="79" vip_level_min="0" vip_level_max="5" bag_1_cost_type="2" bag_1_cost_value="1500" bag_1_cost_time="1" bag_1_item_1_type="3" bag_1_item_1_value="189" bag_1_item_1_size="2" bag_1_item_2_type="3" bag_1_item_2_value="18" bag_1_item_2_size="500" bag_1_item_3_type="0" bag_1_item_3_value="0" bag_1_item_3_size="0" bag_1_item_4_type="0" bag_1_item_4_value="0" bag_1_item_4_size="0" />
    <data id="10030201" level_min="70" level_max="79" vip_level_min="6" vip_level_max="8" bag_1_cost_type="2" bag_1_cost_value="250" bag_1_cost_time="1" bag_1_item_1_type="3" bag_1_item_1_value="5" bag_1_item_1_size="10" bag_1_item_2_type="3" bag_1_item_2_value="4" bag_1_item_2_size="10" bag_1_item_3_type="0" bag_1_item_3_value="0" bag_1_item_3_size="0" bag_1_item_4_type="0" bag_1_item_4_value="0" bag_1_item_4_size="0" />
    <data id="10030202" level_min="70" level_max="79" vip_level_min="6" vip_level_max="8" bag_1_cost_type="2" bag_1_cost_value="350" bag_1_cost_time="2" bag_1_item_1_type="1" bag_1_item_1_value="0" bag_1_item_1_size="1000000" bag_1_item_2_type="0" bag_1_item_2_value="0" bag_1_item_2_size="0" bag_1_item_3_type="0" bag_1_item_3_value="0" bag_1_item_3_size="0" bag_1_item_4_type="0" bag_1_item_4_value="0" bag_1_item_4_size="0" />
    <data id="10030203" level_min="70" level_max="79" vip_level_min="6" vip_level_max="8" bag_1_cost_type="2" bag_1_cost_value="580" bag_1_cost_time="2" bag_1_item_1_type="3" bag_1_item_1_value="21" bag_1_item_1_size="5" bag_1_item_2_type="3" bag_1_item_2_value="13" bag_1_item_2_size="50" bag_1_item_3_type="0" bag_1_item_3_value="0" bag_1_item_3_size="0" bag_1_item_4_type="0" bag_1_item_4_value="0" bag_1_item_4_size="0" />
    <data id="10030204" level_min="70" level_max="79" vip_level_min="6" vip_level_max="8" bag_1_cost_type="2" bag_1_cost_value="1100" bag_1_cost_time="2" bag_1_item_1_type="23" bag_1_item_1_value="0" bag_1_item_1_size="500" bag_1_item_2_type="3" bag_1_item_2_value="60" bag_1_item_2_size="500" bag_1_item_3_type="3" bag_1_item_3_value="74" bag_1_item_3_size="2" bag_1_item_4_type="0" bag_1_item_4_value="0" bag_1_item_4_size="0" />
    <data id="10030205" level_min="70" level_max="79" vip_level_min="6" vip_level_max="8" bag_1_cost_type="2" bag_1_cost_value="1500" bag_1_cost_time="2" bag_1_item_1_type="3" bag_1_item_1_value="189" bag_1_item_1_size="2" bag_1_item_2_type="3" bag_1_item_2_value="18" bag_1_item_2_size="500" bag_1_item_3_type="0" bag_1_item_3_value="0" bag_1_item_3_size="0" bag_1_item_4_type="0" bag_1_item_4_value="0" bag_1_item_4_size="0" />
    <data id="10030301" level_min="70" level_max="79" vip_level_min="9" vip_level_max="12" bag_1_cost_type="2" bag_1_cost_value="250" bag_1_cost_time="1" bag_1_item_1_type="3" bag_1_item_1_value="5" bag_1_item_1_size="10" bag_1_item_2_type="3" bag_1_item_2_value="4" bag_1_item_2_size="10" bag_1_item_3_type="0" bag_1_item_3_value="0" bag_1_item_3_size="0" bag_1_item_4_type="0" bag_1_item_4_value="0" bag_1_item_4_size="0" />
    <data id="10030302" level_min="70" level_max="79" vip_level_min="9" vip_level_max="12" bag_1_cost_type="2" bag_1_cost_value="700" bag_1_cost_time="2" bag_1_item_1_type="1" bag_1_item_1_value="0" bag_1_item_1_size="2000000" bag_1_item_2_type="0" bag_1_item_2_value="0" bag_1_item_2_size="0" bag_1_item_3_type="0" bag_1_item_3_value="0" bag_1_item_3_size="0" bag_1_item_4_type="0" bag_1_item_4_value="0" bag_1_item_4_size="0" />
    <data id="10030303" level_min="70" level_max="79" vip_level_min="9" vip_level_max="12" bag_1_cost_type="2" bag_1_cost_value="580" bag_1_cost_time="3" bag_1_item_1_type="3" bag_1_item_1_value="21" bag_1_item_1_size="5" bag_1_item_2_type="3" bag_1_item_2_value="13" bag_1_item_2_size="50" bag_1_item_3_type="0" bag_1_item_3_value="0" bag_1_item_3_size="0" bag_1_item_4_type="0" bag_1_item_4_value="0" bag_1_item_4_size="0" />
    <data id="10030304" level_min="70" level_max="79" vip_level_min="9" vip_level_max="12" bag_1_cost_type="2" bag_1_cost_value="1100" bag_1_cost_time="3" bag_1_item_1_type="23" bag_1_item_1_value="0" bag_1_item_1_size="500" bag_1_item_2_type="3" bag_1_item_2_value="60" bag_1_item_2_size="500" bag_1_item_3_type="3" bag_1_item_3_value="74" bag_1_item_3_size="2" bag_1_item_4_type="0" bag_1_item_4_value="0" bag_1_item_4_size="0" />
    <data id="10030305" level_min="70" level_max="79" vip_level_min="9" vip_level_max="12" bag_1_cost_type="2" bag_1_cost_value="1500" bag_1_cost_time="3" bag_1_item_1_type="3" bag_1_item_1_value="189" bag_1_item_1_size="2" bag_1_item_2_type="3" bag_1_item_2_value="18" bag_1_item_2_size="500" bag_1_item_3_type="0" bag_1_item_3_value="0" bag_1_item_3_size="0" bag_1_item_4_type="0" bag_1_item_4_value="0" bag_1_item_4_size="0" />
    <data id="10040101" level_min="80" level_max="99" vip_level_min="0" vip_level_max="5" bag_1_cost_type="2" bag_1_cost_value="250" bag_1_cost_time="1" bag_1_item_1_type="3" bag_1_item_1_value="5" bag_1_item_1_size="10" bag_1_item_2_type="3" bag_1_item_2_value="4" bag_1_item_2_size="10" bag_1_item_3_type="0" bag_1_item_3_value="0" bag_1_item_3_size="0" bag_1_item_4_type="0" bag_1_item_4_value="0" bag_1_item_4_size="0" />
    <data id="10040102" level_min="80" level_max="99" vip_level_min="0" vip_level_max="5" bag_1_cost_type="2" bag_1_cost_value="350" bag_1_cost_time="2" bag_1_item_1_type="1" bag_1_item_1_value="0" bag_1_item_1_size="1000000" bag_1_item_2_type="0" bag_1_item_2_value="0" bag_1_item_2_size="0" bag_1_item_3_type="0" bag_1_item_3_value="0" bag_1_item_3_size="0" bag_1_item_4_type="0" bag_1_item_4_value="0" bag_1_item_4_size="0" />
    <data id="10040103" level_min="80" level_max="99" vip_level_min="0" vip_level_max="5" bag_1_cost_type="2" bag_1_cost_value="780" bag_1_cost_time="1" bag_1_item_1_type="3" bag_1_item_1_value="81" bag_1_item_1_size="5" bag_1_item_2_type="3" bag_1_item_2_value="13" bag_1_item_2_size="100" bag_1_item_3_type="0" bag_1_item_3_value="0" bag_1_item_3_size="0" bag_1_item_4_type="0" bag_1_item_4_value="0" bag_1_item_4_size="0" />
    <data id="10040104" level_min="80" level_max="99" vip_level_min="0" vip_level_max="5" bag_1_cost_type="2" bag_1_cost_value="1100" bag_1_cost_time="2" bag_1_item_1_type="23" bag_1_item_1_value="0" bag_1_item_1_size="500" bag_1_item_2_type="3" bag_1_item_2_value="60" bag_1_item_2_size="500" bag_1_item_3_type="3" bag_1_item_3_value="74" bag_1_item_3_size="2" bag_1_item_4_type="0" bag_1_item_4_value="0" bag_1_item_4_size="0" />
    <data id="10040105" level_min="80" level_max="99" vip_level_min="0" vip_level_max="5" bag_1_cost_type="2" bag_1_cost_value="1500" bag_1_cost_time="1" bag_1_item_1_type="3" bag_1_item_1_value="189" bag_1_item_1_size="2" bag_1_item_2_type="3" bag_1_item_2_value="18" bag_1_item_2_size="500" bag_1_item_3_type="0" bag_1_item_3_value="0" bag_1_item_3_size="0" bag_1_item_4_type="0" bag_1_item_4_value="0" bag_1_item_4_size="0" />
    <data id="10040201" level_min="80" level_max="99" vip_level_min="6" vip_level_max="8" bag_1_cost_type="2" bag_1_cost_value="250" bag_1_cost_time="1" bag_1_item_1_type="3" bag_1_item_1_value="5" bag_1_item_1_size="10" bag_1_item_2_type="3" bag_1_item_2_value="4" bag_1_item_2_size="10" bag_1_item_3_type="0" bag_1_item_3_value="0" bag_1_item_3_size="0" bag_1_item_4_type="0" bag_1_item_4_value="0" bag_1_item_4_size="0" />
    <data id="10040202" level_min="80" level_max="99" vip_level_min="6" vip_level_max="8" bag_1_cost_type="2" bag_1_cost_value="525" bag_1_cost_time="2" bag_1_item_1_type="1" bag_1_item_1_value="0" bag_1_item_1_size="1500000" bag_1_item_2_type="0" bag_1_item_2_value="0" bag_1_item_2_size="0" bag_1_item_3_type="0" bag_1_item_3_value="0" bag_1_item_3_size="0" bag_1_item_4_type="0" bag_1_item_4_value="0" bag_1_item_4_size="0" />
    <data id="10040203" level_min="80" level_max="99" vip_level_min="6" vip_level_max="8" bag_1_cost_type="2" bag_1_cost_value="780" bag_1_cost_time="2" bag_1_item_1_type="3" bag_1_item_1_value="81" bag_1_item_1_size="5" bag_1_item_2_type="3" bag_1_item_2_value="13" bag_1_item_2_size="100" bag_1_item_3_type="0" bag_1_item_3_value="0" bag_1_item_3_size="0" bag_1_item_4_type="0" bag_1_item_4_value="0" bag_1_item_4_size="0" />
    <data id="10040204" level_min="80" level_max="99" vip_level_min="6" vip_level_max="8" bag_1_cost_type="2" bag_1_cost_value="1100" bag_1_cost_time="3" bag_1_item_1_type="23" bag_1_item_1_value="0" bag_1_item_1_size="500" bag_1_item_2_type="3" bag_1_item_2_value="60" bag_1_item_2_size="500" bag_1_item_3_type="3" bag_1_item_3_value="74" bag_1_item_3_size="2" bag_1_item_4_type="0" bag_1_item_4_value="0" bag_1_item_4_size="0" />
    <data id="10040205" level_min="80" level_max="99" vip_level_min="6" vip_level_max="8" bag_1_cost_type="2" bag_1_cost_value="1500" bag_1_cost_time="2" bag_1_item_1_type="3" bag_1_item_1_value="189" bag_1_item_1_size="2" bag_1_item_2_type="3" bag_1_item_2_value="18" bag_1_item_2_size="500" bag_1_item_3_type="0" bag_1_item_3_value="0" bag_1_item_3_size="0" bag_1_item_4_type="0" bag_1_item_4_value="0" bag_1_item_4_size="0" />
    <data id="10040301" level_min="80" level_max="99" vip_level_min="9" vip_level_max="12" bag_1_cost_type="2" bag_1_cost_value="250" bag_1_cost_time="1" bag_1_item_1_type="3" bag_1_item_1_value="5" bag_1_item_1_size="10" bag_1_item_2_type="3" bag_1_item_2_value="4" bag_1_item_2_size="10" bag_1_item_3_type="0" bag_1_item_3_value="0" bag_1_item_3_size="0" bag_1_item_4_type="0" bag_1_item_4_value="0" bag_1_item_4_size="0" />
    <data id="10040302" level_min="80" level_max="99" vip_level_min="9" vip_level_max="12" bag_1_cost_type="2" bag_1_cost_value="700" bag_1_cost_time="2" bag_1_item_1_type="1" bag_1_item_1_value="0" bag_1_item_1_size="2000000" bag_1_item_2_type="0" bag_1_item_2_value="0" bag_1_item_2_size="0" bag_1_item_3_type="0" bag_1_item_3_value="0" bag_1_item_3_size="0" bag_1_item_4_type="0" bag_1_item_4_value="0" bag_1_item_4_size="0" />
    <data id="10040303" level_min="80" level_max="99" vip_level_min="9" vip_level_max="12" bag_1_cost_type="2" bag_1_cost_value="780" bag_1_cost_time="3" bag_1_item_1_type="3" bag_1_item_1_value="81" bag_1_item_1_size="5" bag_1_item_2_type="3" bag_1_item_2_value="13" bag_1_item_2_size="100" bag_1_item_3_type="0" bag_1_item_3_value="0" bag_1_item_3_size="0" bag_1_item_4_type="0" bag_1_item_4_value="0" bag_1_item_4_size="0" />
    <data id="10040304" level_min="80" level_max="99" vip_level_min="9" vip_level_max="12" bag_1_cost_type="2" bag_1_cost_value="1100" bag_1_cost_time="4" bag_1_item_1_type="23" bag_1_item_1_value="0" bag_1_item_1_size="500" bag_1_item_2_type="3" bag_1_item_2_value="60" bag_1_item_2_size="500" bag_1_item_3_type="3" bag_1_item_3_value="74" bag_1_item_3_size="2" bag_1_item_4_type="0" bag_1_item_4_value="0" bag_1_item_4_size="0" />
    <data id="10040305" level_min="80" level_max="99" vip_level_min="9" vip_level_max="12" bag_1_cost_type="2" bag_1_cost_value="1500" bag_1_cost_time="3" bag_1_item_1_type="3" bag_1_item_1_value="189" bag_1_item_1_size="2" bag_1_item_2_type="3" bag_1_item_2_value="18" bag_1_item_2_size="500" bag_1_item_3_type="0" bag_1_item_3_value="0" bag_1_item_3_size="0" bag_1_item_4_type="0" bag_1_item_4_value="0" bag_1_item_4_size="0" />
    <data id="10050101" level_min="100" level_max="150" vip_level_min="0" vip_level_max="5" bag_1_cost_type="2" bag_1_cost_value="250" bag_1_cost_time="1" bag_1_item_1_type="3" bag_1_item_1_value="5" bag_1_item_1_size="10" bag_1_item_2_type="3" bag_1_item_2_value="4" bag_1_item_2_size="10" bag_1_item_3_type="0" bag_1_item_3_value="0" bag_1_item_3_size="0" bag_1_item_4_type="0" bag_1_item_4_value="0" bag_1_item_4_size="0" />
    <data id="10050102" level_min="100" level_max="150" vip_level_min="0" vip_level_max="5" bag_1_cost_type="2" bag_1_cost_value="350" bag_1_cost_time="3" bag_1_item_1_type="1" bag_1_item_1_value="0" bag_1_item_1_size="1000000" bag_1_item_2_type="0" bag_1_item_2_value="0" bag_1_item_2_size="0" bag_1_item_3_type="0" bag_1_item_3_value="0" bag_1_item_3_size="0" bag_1_item_4_type="0" bag_1_item_4_value="0" bag_1_item_4_size="0" />
    <data id="10050103" level_min="100" level_max="150" vip_level_min="0" vip_level_max="5" bag_1_cost_type="2" bag_1_cost_value="780" bag_1_cost_time="2" bag_1_item_1_type="3" bag_1_item_1_value="81" bag_1_item_1_size="5" bag_1_item_2_type="3" bag_1_item_2_value="13" bag_1_item_2_size="100" bag_1_item_3_type="0" bag_1_item_3_value="0" bag_1_item_3_size="0" bag_1_item_4_type="0" bag_1_item_4_value="0" bag_1_item_4_size="0" />
    <data id="10050104" level_min="100" level_max="150" vip_level_min="0" vip_level_max="5" bag_1_cost_type="2" bag_1_cost_value="1500" bag_1_cost_time="2" bag_1_item_1_type="23" bag_1_item_1_value="0" bag_1_item_1_size="500" bag_1_item_2_type="3" bag_1_item_2_value="60" bag_1_item_2_size="500" bag_1_item_3_type="3" bag_1_item_3_value="75" bag_1_item_3_size="1" bag_1_item_4_type="0" bag_1_item_4_value="0" bag_1_item_4_size="0" />
    <data id="10050105" level_min="100" level_max="150" vip_level_min="0" vip_level_max="5" bag_1_cost_type="2" bag_1_cost_value="1500" bag_1_cost_time="2" bag_1_item_1_type="3" bag_1_item_1_value="189" bag_1_item_1_size="2" bag_1_item_2_type="3" bag_1_item_2_value="18" bag_1_item_2_size="500" bag_1_item_3_type="0" bag_1_item_3_value="0" bag_1_item_3_size="0" bag_1_item_4_type="0" bag_1_item_4_value="0" bag_1_item_4_size="0" />
    <data id="10050201" level_min="100" level_max="150" vip_level_min="6" vip_level_max="8" bag_1_cost_type="2" bag_1_cost_value="250" bag_1_cost_time="1" bag_1_item_1_type="3" bag_1_item_1_value="5" bag_1_item_1_size="10" bag_1_item_2_type="3" bag_1_item_2_value="4" bag_1_item_2_size="10" bag_1_item_3_type="0" bag_1_item_3_value="0" bag_1_item_3_size="0" bag_1_item_4_type="0" bag_1_item_4_value="0" bag_1_item_4_size="0" />
    <data id="10050202" level_min="100" level_max="150" vip_level_min="6" vip_level_max="8" bag_1_cost_type="2" bag_1_cost_value="525" bag_1_cost_time="3" bag_1_item_1_type="1" bag_1_item_1_value="0" bag_1_item_1_size="1500000" bag_1_item_2_type="0" bag_1_item_2_value="0" bag_1_item_2_size="0" bag_1_item_3_type="0" bag_1_item_3_value="0" bag_1_item_3_size="0" bag_1_item_4_type="0" bag_1_item_4_value="0" bag_1_item_4_size="0" />
    <data id="10050203" level_min="100" level_max="150" vip_level_min="6" vip_level_max="8" bag_1_cost_type="2" bag_1_cost_value="780" bag_1_cost_time="3" bag_1_item_1_type="3" bag_1_item_1_value="81" bag_1_item_1_size="5" bag_1_item_2_type="3" bag_1_item_2_value="13" bag_1_item_2_size="100" bag_1_item_3_type="0" bag_1_item_3_value="0" bag_1_item_3_size="0" bag_1_item_4_type="0" bag_1_item_4_value="0" bag_1_item_4_size="0" />
    <data id="10050204" level_min="100" level_max="150" vip_level_min="6" vip_level_max="8" bag_1_cost_type="2" bag_1_cost_value="1500" bag_1_cost_time="4" bag_1_item_1_type="23" bag_1_item_1_value="0" bag_1_item_1_size="500" bag_1_item_2_type="3" bag_1_item_2_value="60" bag_1_item_2_size="500" bag_1_item_3_type="3" bag_1_item_3_value="75" bag_1_item_3_size="1" bag_1_item_4_type="0" bag_1_item_4_value="0" bag_1_item_4_size="0" />
    <data id="10050205" level_min="100" level_max="150" vip_level_min="6" vip_level_max="8" bag_1_cost_type="2" bag_1_cost_value="1500" bag_1_cost_time="3" bag_1_item_1_type="3" bag_1_item_1_value="189" bag_1_item_1_size="2" bag_1_item_2_type="3" bag_1_item_2_value="18" bag_1_item_2_size="500" bag_1_item_3_type="0" bag_1_item_3_value="0" bag_1_item_3_size="0" bag_1_item_4_type="0" bag_1_item_4_value="0" bag_1_item_4_size="0" />
    <data id="10050301" level_min="100" level_max="150" vip_level_min="9" vip_level_max="12" bag_1_cost_type="2" bag_1_cost_value="250" bag_1_cost_time="1" bag_1_item_1_type="3" bag_1_item_1_value="5" bag_1_item_1_size="10" bag_1_item_2_type="3" bag_1_item_2_value="4" bag_1_item_2_size="10" bag_1_item_3_type="0" bag_1_item_3_value="0" bag_1_item_3_size="0" bag_1_item_4_type="0" bag_1_item_4_value="0" bag_1_item_4_size="0" />
    <data id="10050302" level_min="100" level_max="150" vip_level_min="9" vip_level_max="12" bag_1_cost_type="2" bag_1_cost_value="700" bag_1_cost_time="3" bag_1_item_1_type="1" bag_1_item_1_value="0" bag_1_item_1_size="2000000" bag_1_item_2_type="0" bag_1_item_2_value="0" bag_1_item_2_size="0" bag_1_item_3_type="0" bag_1_item_3_value="0" bag_1_item_3_size="0" bag_1_item_4_type="0" bag_1_item_4_value="0" bag_1_item_4_size="0" />
    <data id="10050303" level_min="100" level_max="150" vip_level_min="9" vip_level_max="12" bag_1_cost_type="2" bag_1_cost_value="780" bag_1_cost_time="4" bag_1_item_1_type="3" bag_1_item_1_value="81" bag_1_item_1_size="5" bag_1_item_2_type="3" bag_1_item_2_value="13" bag_1_item_2_size="100" bag_1_item_3_type="0" bag_1_item_3_value="0" bag_1_item_3_size="0" bag_1_item_4_type="0" bag_1_item_4_value="0" bag_1_item_4_size="0" />
    <data id="10050304" level_min="100" level_max="150" vip_level_min="9" vip_level_max="12" bag_1_cost_type="2" bag_1_cost_value="1500" bag_1_cost_time="6" bag_1_item_1_type="23" bag_1_item_1_value="0" bag_1_item_1_size="500" bag_1_item_2_type="3" bag_1_item_2_value="60" bag_1_item_2_size="500" bag_1_item_3_type="3" bag_1_item_3_value="75" bag_1_item_3_size="1" bag_1_item_4_type="0" bag_1_item_4_value="0" bag_1_item_4_size="0" />
    <data id="10050305" level_min="100" level_max="150" vip_level_min="9" vip_level_max="12" bag_1_cost_type="2" bag_1_cost_value="1500" bag_1_cost_time="4" bag_1_item_1_type="3" bag_1_item_1_value="189" bag_1_item_1_size="2" bag_1_item_2_type="3" bag_1_item_2_value="18" bag_1_item_2_size="500" bag_1_item_3_type="0" bag_1_item_3_value="0" bag_1_item_3_size="0" bag_1_item_4_type="0" bag_1_item_4_value="0" bag_1_item_4_size="0" />
</root>