{
  "DFH_1" : {
    "f1" : {
      "start" : {
        "x" : "-329.45",
        "y" : "693.85",
        "rotation" : "0",
        "scaleX" : "-1.2",
        "scaleY" : "1.2",
        "opacity" : "0",
        "png" : "effect_sunshine_gs_1.png"
      },
      "nextFrame" : "f30",
      "frames" : "30"
    },
    "order" : "7",
    "f30" : {
      "start" : {
        "x" : "-329.7",
        "y" : "693.7",
        "rotation" : "3.78",
        "scaleX" : "-2",
        "scaleY" : "2",
        "opacity" : "135",
        "png" : "effect_sunshine_gs_1.png"
      }
    },
    "f90" : {
      "start" : {
        "x" : "-329.7",
        "y" : "693.7",
        "rotation" : "3.78",
        "scaleX" : "-2",
        "scaleY" : "2",
        "opacity" : "76",
        "png" : "effect_sunshine_gs_1.png"
      },
      "nextFrame" : "f113",
      "frames" : "24"
    },
    "f113" : {
      "start" : {
        "x" : "-329.7",
        "y" : "693.7",
        "rotation" : "3.78",
        "scaleX" : "-2",
        "scaleY" : "2",
        "opacity" : "0",
        "png" : "effect_sunshine_gs_1.png"
      }
    }
  },
  "gh 复制_2" : {
    "f24" : {
      "start" : {
        "x" : "-178.35",
        "y" : "711.05",
        "rotation" : "-173.62",
        "scaleX" : "-1.05",
        "scaleY" : "1.02",
        "opacity" : "0",
        "png" : "effect_sunshine_gs_2.png"
      },
      "nextFrame" : "f39",
      "frames" : "16"
    },
    "order" : "6",
    "f39" : {
      "start" : {
        "x" : "-178",
        "y" : "705.85",
        "rotation" : "-171.62",
        "scaleX" : "-1.05",
        "scaleY" : "1.02",
        "opacity" : "135",
        "png" : "effect_sunshine_gs_2.png"
      },
      "nextFrame" : "f55",
      "frames" : "17"
    },
    "f55" : {
      "start" : {
        "x" : "-177.85",
        "y" : "699.2",
        "rotation" : "-169.18",
        "scaleX" : "-1.05",
        "scaleY" : "1.02",
        "opacity" : "135",
        "png" : "effect_sunshine_gs_2.png"
      },
      "nextFrame" : "f71",
      "frames" : "17"
    },
    "f71" : {
      "start" : {
        "x" : "-178.2",
        "y" : "693.05",
        "rotation" : "-166.89",
        "scaleX" : "-1.05",
        "scaleY" : "1.02",
        "opacity" : "102",
        "png" : "effect_sunshine_gs_2.png"
      },
      "nextFrame" : "f90",
      "frames" : "20"
    },
    "f90" : {
      "start" : {
        "x" : "-178.3",
        "y" : "686.75",
        "rotation" : "-164.48",
        "scaleX" : "-1.05",
        "scaleY" : "1.02",
        "opacity" : "76",
        "png" : "effect_sunshine_gs_2.png"
      },
      "nextFrame" : "f113",
      "frames" : "24"
    },
    "f113" : {
      "start" : {
        "x" : "-178.2",
        "y" : "682.35",
        "rotation" : "-162.77",
        "scaleX" : "-1.05",
        "scaleY" : "1.02",
        "opacity" : "0",
        "png" : "effect_sunshine_gs_2.png"
      }
    }
  },
  "gh_3" : {
    "f24" : {
      "start" : {
        "x" : "-182.4",
        "y" : "663",
        "rotation" : "-154.99",
        "scaleX" : "-1.05",
        "scaleY" : "1.02",
        "opacity" : "0",
        "png" : "effect_sunshine_gs_2.png"
      },
      "nextFrame" : "f39",
      "frames" : "16"
    },
    "order" : "5",
    "f39" : {
      "start" : {
        "x" : "-183.95",
        "y" : "657.95",
        "rotation" : "-153",
        "scaleX" : "-1.05",
        "scaleY" : "1.02",
        "opacity" : "135",
        "png" : "effect_sunshine_gs_2.png"
      },
      "nextFrame" : "f55",
      "frames" : "17"
    },
    "f55" : {
      "start" : {
        "x" : "-185.75",
        "y" : "651.65",
        "rotation" : "-150.55",
        "scaleX" : "-1.05",
        "scaleY" : "1.02",
        "opacity" : "135",
        "png" : "effect_sunshine_gs_2.png"
      },
      "nextFrame" : "f71",
      "frames" : "17"
    },
    "f71" : {
      "start" : {
        "x" : "-188",
        "y" : "645.95",
        "rotation" : "-148.26",
        "scaleX" : "-1.05",
        "scaleY" : "1.02",
        "opacity" : "102",
        "png" : "effect_sunshine_gs_2.png"
      },
      "nextFrame" : "f90",
      "frames" : "20"
    },
    "f90" : {
      "start" : {
        "x" : "-190.1",
        "y" : "639.95",
        "rotation" : "-145.86",
        "scaleX" : "-1.05",
        "scaleY" : "1.02",
        "opacity" : "76",
        "png" : "effect_sunshine_gs_2.png"
      },
      "nextFrame" : "f113",
      "frames" : "24"
    },
    "f113" : {
      "start" : {
        "x" : "-191.45",
        "y" : "635.75",
        "rotation" : "-144.15",
        "scaleX" : "-1.05",
        "scaleY" : "1.02",
        "opacity" : "0",
        "png" : "effect_sunshine_gs_2.png"
      }
    }
  },
  "gh_4" : {
    "f24" : {
      "start" : {
        "x" : "-439.85",
        "y" : "595.3",
        "rotation" : "-33.83",
        "scaleX" : "-1.04",
        "scaleY" : "1.02",
        "opacity" : "0",
        "png" : "effect_sunshine_gs_2.png"
      },
      "nextFrame" : "f39",
      "frames" : "16"
    },
    "order" : "4",
    "f39" : {
      "start" : {
        "x" : "-443.35",
        "y" : "599.4",
        "rotation" : "-31.8",
        "scaleX" : "-1.04",
        "scaleY" : "1.02",
        "opacity" : "135",
        "png" : "effect_sunshine_gs_2.png"
      },
      "nextFrame" : "f55",
      "frames" : "17"
    },
    "f55" : {
      "start" : {
        "x" : "-447.6",
        "y" : "604",
        "rotation" : "-29.39",
        "scaleX" : "-1.04",
        "scaleY" : "1.02",
        "opacity" : "135",
        "png" : "effect_sunshine_gs_2.png"
      },
      "nextFrame" : "f71",
      "frames" : "17"
    },
    "f71" : {
      "start" : {
        "x" : "-451.3",
        "y" : "609",
        "rotation" : "-27.05",
        "scaleX" : "-1.04",
        "scaleY" : "1.02",
        "opacity" : "102",
        "png" : "effect_sunshine_gs_2.png"
      },
      "nextFrame" : "f90",
      "frames" : "20"
    },
    "f90" : {
      "start" : {
        "x" : "-455.1",
        "y" : "613.95",
        "rotation" : "-24.69",
        "scaleX" : "-1.04",
        "scaleY" : "1.02",
        "opacity" : "76",
        "png" : "effect_sunshine_gs_2.png"
      },
      "nextFrame" : "f113",
      "frames" : "24"
    },
    "f113" : {
      "start" : {
        "x" : "-456.95",
        "y" : "617.95",
        "rotation" : "-22.98",
        "scaleX" : "-1.04",
        "scaleY" : "1.02",
        "opacity" : "0",
        "png" : "effect_sunshine_gs_2.png"
      }
    }
  },
  "gh_5" : {
    "f24" : {
      "start" : {
        "x" : "-387.6",
        "y" : "562.3",
        "rotation" : "-56.72",
        "scaleX" : "-1.04",
        "scaleY" : "1.02",
        "opacity" : "0",
        "png" : "effect_sunshine_gs_2.png"
      },
      "nextFrame" : "f39",
      "frames" : "16"
    },
    "order" : "3",
    "f39" : {
      "start" : {
        "x" : "-392.25",
        "y" : "564.6",
        "rotation" : "-54.73",
        "scaleX" : "-1.04",
        "scaleY" : "1.02",
        "opacity" : "135",
        "png" : "effect_sunshine_gs_2.png"
      },
      "nextFrame" : "f55",
      "frames" : "17"
    },
    "f55" : {
      "start" : {
        "x" : "-398.15",
        "y" : "567.25",
        "rotation" : "-52.28",
        "scaleX" : "-1.04",
        "scaleY" : "1.02",
        "opacity" : "135",
        "png" : "effect_sunshine_gs_2.png"
      },
      "nextFrame" : "f71",
      "frames" : "17"
    },
    "f71" : {
      "start" : {
        "x" : "-403.3",
        "y" : "570.2",
        "rotation" : "-49.99",
        "scaleX" : "-1.04",
        "scaleY" : "1.02",
        "opacity" : "102",
        "png" : "effect_sunshine_gs_2.png"
      },
      "nextFrame" : "f90",
      "frames" : "20"
    },
    "f90" : {
      "start" : {
        "x" : "-408.75",
        "y" : "573.15",
        "rotation" : "-47.58",
        "scaleX" : "-1.04",
        "scaleY" : "1.02",
        "opacity" : "76",
        "png" : "effect_sunshine_gs_2.png"
      },
      "nextFrame" : "f113",
      "frames" : "24"
    },
    "f113" : {
      "start" : {
        "x" : "-411.95",
        "y" : "575.6",
        "rotation" : "-45.87",
        "scaleX" : "-1.04",
        "scaleY" : "1.02",
        "opacity" : "0",
        "png" : "effect_sunshine_gs_2.png"
      }
    }
  },
  "gh_6" : {
    "f24" : {
      "start" : {
        "x" : "-208.85",
        "y" : "605",
        "rotation" : "-131.55",
        "scaleX" : "-1.04",
        "scaleY" : "1.02",
        "opacity" : "0",
        "png" : "effect_sunshine_gs_2.png"
      },
      "nextFrame" : "f39",
      "frames" : "16"
    },
    "order" : "2",
    "f39" : {
      "start" : {
        "x" : "-212.5",
        "y" : "600.65",
        "rotation" : "-129.46",
        "scaleX" : "-1.04",
        "scaleY" : "1.02",
        "opacity" : "135",
        "png" : "effect_sunshine_gs_2.png"
      },
      "nextFrame" : "f55",
      "frames" : "17"
    },
    "f55" : {
      "start" : {
        "x" : "-216.55",
        "y" : "595.8",
        "rotation" : "-127.1",
        "scaleX" : "-1.04",
        "scaleY" : "1.02",
        "opacity" : "135",
        "png" : "effect_sunshine_gs_2.png"
      },
      "nextFrame" : "f71",
      "frames" : "17"
    },
    "f71" : {
      "start" : {
        "x" : "-221.2",
        "y" : "591.35",
        "rotation" : "-124.71",
        "scaleX" : "-1.04",
        "scaleY" : "1.02",
        "opacity" : "102",
        "png" : "effect_sunshine_gs_2.png"
      },
      "nextFrame" : "f90",
      "frames" : "20"
    },
    "f90" : {
      "start" : {
        "x" : "-225.35",
        "y" : "586.85",
        "rotation" : "-122.41",
        "scaleX" : "-1.04",
        "scaleY" : "1.02",
        "opacity" : "76",
        "png" : "effect_sunshine_gs_2.png"
      },
      "nextFrame" : "f113",
      "frames" : "24"
    },
    "f113" : {
      "start" : {
        "x" : "-228.2",
        "y" : "583.9",
        "rotation" : "-120.7",
        "scaleX" : "-1.04",
        "scaleY" : "1.02",
        "opacity" : "0",
        "png" : "effect_sunshine_gs_2.png"
      }
    }
  },
  "gh_7" : {
    "f24" : {
      "start" : {
        "x" : "-284.1",
        "y" : "552.1",
        "rotation" : "-96.71",
        "scaleX" : "-1.04",
        "scaleY" : "1.02",
        "opacity" : "0",
        "png" : "effect_sunshine_gs_2.png"
      },
      "nextFrame" : "f39",
      "frames" : "16"
    },
    "order" : "1",
    "f39" : {
      "start" : {
        "x" : "-289.7",
        "y" : "550.6",
        "rotation" : "-94.59",
        "scaleX" : "-1.04",
        "scaleY" : "1.02",
        "opacity" : "135",
        "png" : "effect_sunshine_gs_2.png"
      },
      "nextFrame" : "f55",
      "frames" : "17"
    },
    "f55" : {
      "start" : {
        "x" : "-295.75",
        "y" : "549",
        "rotation" : "-92.26",
        "scaleX" : "-1.04",
        "scaleY" : "1.02",
        "opacity" : "135",
        "png" : "effect_sunshine_gs_2.png"
      },
      "nextFrame" : "f71",
      "frames" : "17"
    },
    "f71" : {
      "start" : {
        "x" : "-302.05",
        "y" : "547.75",
        "rotation" : "-89.84",
        "scaleX" : "-1.04",
        "scaleY" : "1.02",
        "opacity" : "102",
        "png" : "effect_sunshine_gs_2.png"
      },
      "nextFrame" : "f90",
      "frames" : "20"
    },
    "f90" : {
      "start" : {
        "x" : "-308.15",
        "y" : "546.6",
        "rotation" : "-87.57",
        "scaleX" : "-1.04",
        "scaleY" : "1.02",
        "opacity" : "76",
        "png" : "effect_sunshine_gs_2.png"
      },
      "nextFrame" : "f113",
      "frames" : "24"
    },
    "f113" : {
      "start" : {
        "x" : "-312.15",
        "y" : "546.05",
        "rotation" : "-85.86",
        "scaleX" : "-1.04",
        "scaleY" : "1.02",
        "opacity" : "0",
        "png" : "effect_sunshine_gs_2.png"
      }
    }
  },
  "图层 46_8" : {
    "f24" : {
      "start" : {
        "x" : "-260.75",
        "y" : "595.65",
        "rotation" : "-87.02",
        "scaleX" : "-0.98",
        "scaleY" : "0.98",
        "opacity" : "0",
        "png" : "effect_sunshine_gs_3.png"
      },
      "nextFrame" : "f55",
      "frames" : "32"
    },
    "order" : "0",
    "f55" : {
      "start" : {
        "x" : "-273.75",
        "y" : "588.2",
        "rotation" : "-80.09",
        "scaleX" : "-0.98",
        "scaleY" : "0.98",
        "opacity" : "255",
        "png" : "effect_sunshine_gs_3.png"
      },
      "nextFrame" : "f71",
      "frames" : "17"
    },
    "f71" : {
      "start" : {
        "x" : "-284.4",
        "y" : "584.05",
        "rotation" : "-74.95",
        "scaleX" : "-0.98",
        "scaleY" : "0.98",
        "opacity" : "255",
        "png" : "effect_sunshine_gs_3.png"
      },
      "nextFrame" : "f90",
      "frames" : "20"
    },
    "f90" : {
      "start" : {
        "x" : "-295.15",
        "y" : "579.95",
        "rotation" : "-69.58",
        "scaleX" : "-0.98",
        "scaleY" : "0.98",
        "opacity" : "255",
        "png" : "effect_sunshine_gs_3.png"
      },
      "nextFrame" : "f113",
      "frames" : "24"
    },
    "f113" : {
      "start" : {
        "x" : "-300.45",
        "y" : "578.6",
        "rotation" : "-66.84",
        "scaleX" : "-0.98",
        "scaleY" : "0.98",
        "opacity" : "0",
        "png" : "effect_sunshine_gs_3.png"
      }
    }
  },
  "events" : {
    "f340" : "forever"
  },
  "scale" : "1",
  "png" : "effect_sunshine_gs.png"
}