{
  "base_layer" : {
    "f1" : {
      "start" : {
        "x" : "0",
        "y" : "0",
        "rotation" : "0",
        "scaleX" : "1",
        "scaleY" : "1",
        "opacity" : "255"
      }
    },
    "f4" : {
      "start" : {
        "x" : "0",
        "y" : "0",
        "rotation" : "0",
        "scaleX" : "1",
        "scaleY" : "1",
        "opacity" : "255"
      },
      "nextFrame" : "f7",
      "frames" : "4"
    },
    "f7" : {
      "start" : {
        "x" : "0",
        "y" : "0",
        "rotation" : "0",
        "scaleX" : "1",
        "scaleY" : "1",
        "color" : {
          "alpha_original" : "1",
          "alpha" : "0",
          "red_original" : "1",
          "red" : "150",
          "green_original" : "1",
          "green" : "40",
          "blue_original" : "1",
          "blue" : "-255"
        }
      }
    },
    "f8" : {
      "start" : {
        "x" : "0",
        "y" : "0",
        "rotation" : "0",
        "scaleX" : "1",
        "scaleY" : "1",
        "color" : {
          "alpha_original" : "1",
          "alpha" : "0",
          "red_original" : "1",
          "red" : "0",
          "green_original" : "1",
          "green" : "0",
          "blue_original" : "1",
          "blue" : "0"
        }
      }
    },
    "f9" : {
      "start" : {
        "x" : "0",
        "y" : "0",
        "rotation" : "0",
        "scaleX" : "1",
        "scaleY" : "1",
        "color" : {
          "alpha_original" : "1",
          "alpha" : "0",
          "red_original" : "1",
          "red" : "0",
          "green_original" : "1",
          "green" : "0",
          "blue_original" : "1",
          "blue" : "0"
        }
      }
    },
    "f10" : {
      "start" : {
        "x" : "0",
        "y" : "0",
        "rotation" : "0",
        "scaleX" : "1",
        "scaleY" : "1",
        "color" : {
          "alpha_original" : "1",
          "alpha" : "0",
          "red_original" : "1",
          "red" : "0",
          "green_original" : "1",
          "green" : "0",
          "blue_original" : "1",
          "blue" : "0"
        }
      }
    },
    "f11" : {
      "start" : {
        "x" : "0",
        "y" : "0",
        "rotation" : "0",
        "scaleX" : "1",
        "scaleY" : "1",
        "color" : {
          "alpha_original" : "1",
          "alpha" : "0",
          "red_original" : "1",
          "red" : "150",
          "green_original" : "1",
          "green" : "40",
          "blue_original" : "1",
          "blue" : "-255"
        }
      }
    },
    "f12" : {
      "start" : {
        "x" : "0",
        "y" : "0",
        "rotation" : "0",
        "scaleX" : "1",
        "scaleY" : "1",
        "color" : {
          "alpha_original" : "1",
          "alpha" : "0",
          "red_original" : "1",
          "red" : "150",
          "green_original" : "1",
          "green" : "40",
          "blue_original" : "1",
          "blue" : "-255"
        }
      },
      "nextFrame" : "f15",
      "frames" : "4"
    },
    "f15" : {
      "start" : {
        "x" : "-141.8",
        "y" : "-171.2",
        "rotation" : "0",
        "scaleX" : "1",
        "scaleY" : "1",
        "color" : {
          "alpha_original" : "1",
          "alpha" : "0",
          "red_original" : "1",
          "red" : "109",
          "green_original" : "1",
          "green" : "29",
          "blue_original" : "1",
          "blue" : "-185"
        }
      },
      "nextFrame" : "f19",
      "frames" : "5"
    },
    "f19" : {
      "start" : {
        "x" : "-211.05",
        "y" : "-242.9",
        "rotation" : "0",
        "scaleX" : "1",
        "scaleY" : "1",
        "color" : {
          "alpha_original" : "1",
          "alpha" : "0",
          "red_original" : "1",
          "red" : "150",
          "green_original" : "1",
          "green" : "40",
          "blue_original" : "1",
          "blue" : "-255"
        }
      },
      "nextFrame" : "f22",
      "frames" : "4"
    },
    "f22" : {
      "start" : {
        "x" : "-239.05",
        "y" : "-264.9",
        "rotation" : "0",
        "scaleX" : "1",
        "scaleY" : "1",
        "color" : {
          "alpha_original" : "0",
          "alpha" : "0",
          "red_original" : "1",
          "red" : "150",
          "green_original" : "1",
          "green" : "40",
          "blue_original" : "1",
          "blue" : "-255"
        }
      }
    },
    "f33" : {
      "start" : {
        "x" : "94.75",
        "y" : "-237.35",
        "rotation" : "0",
        "scaleX" : "0.91",
        "scaleY" : "0.91",
        "color" : {
          "alpha_original" : "0",
          "alpha" : "0",
          "red_original" : "1",
          "red" : "150",
          "green_original" : "1",
          "green" : "40",
          "blue_original" : "1",
          "blue" : "-255"
        }
      },
      "nextFrame" : "f36",
      "frames" : "4"
    },
    "f36" : {
      "start" : {
        "x" : "0",
        "y" : "0",
        "rotation" : "0",
        "scaleX" : "1",
        "scaleY" : "1",
        "color" : {
          "alpha_original" : "1",
          "alpha" : "0",
          "red_original" : "1",
          "red" : "0",
          "green_original" : "1",
          "green" : "0",
          "blue_original" : "1",
          "blue" : "0"
        }
      }
    }
  },
  "card_layer" : {
    "f1" : {
      "start" : {
        "x" : "0",
        "y" : "0",
        "rotation" : "-8",
        "scaleX" : "1",
        "scaleY" : "1",
        "opacity" : "255"
      },
      "nextFrame" : "f4",
      "frames" : "4"
    },
    "f4" : {
      "start" : {
        "x" : "0",
        "y" : "0",
        "rotation" : "0",
        "scaleX" : "1.03",
        "scaleY" : "0.93",
        "opacity" : "255"
      },
      "nextFrame" : "f7",
      "frames" : "4"
    },
    "f7" : {
      "start" : {
        "x" : "0",
        "y" : "0",
        "rotation" : "0",
        "scaleX" : "1.05",
        "scaleY" : "0.87",
        "color" : {
          "alpha_original" : "1",
          "alpha" : "0",
          "red_original" : "1",
          "red" : "150",
          "green_original" : "1",
          "green" : "40",
          "blue_original" : "1",
          "blue" : "-255"
        }
      }
    },
    "f8" : {
      "start" : {
        "x" : "0",
        "y" : "0",
        "rotation" : "0",
        "scaleX" : "1.05",
        "scaleY" : "0.87",
        "color" : {
          "alpha_original" : "1",
          "alpha" : "0",
          "red_original" : "1",
          "red" : "0",
          "green_original" : "1",
          "green" : "0",
          "blue_original" : "1",
          "blue" : "0"
        }
      }
    },
    "f9" : {
      "start" : {
        "x" : "0",
        "y" : "-0.15",
        "rotation" : "0",
        "scaleX" : "1.05",
        "scaleY" : "0.87",
        "color" : {
          "alpha_original" : "1",
          "alpha" : "0",
          "red_original" : "1",
          "red" : "0",
          "green_original" : "1",
          "green" : "0",
          "blue_original" : "1",
          "blue" : "0"
        }
      }
    },
    "f10" : {
      "start" : {
        "x" : "0",
        "y" : "0",
        "rotation" : "0",
        "scaleX" : "1.05",
        "scaleY" : "0.87",
        "color" : {
          "alpha_original" : "1",
          "alpha" : "0",
          "red_original" : "1",
          "red" : "0",
          "green_original" : "1",
          "green" : "0",
          "blue_original" : "1",
          "blue" : "0"
        }
      }
    },
    "f11" : {
      "start" : {
        "x" : "0",
        "y" : "0",
        "rotation" : "0",
        "scaleX" : "1.05",
        "scaleY" : "0.87",
        "color" : {
          "alpha_original" : "1",
          "alpha" : "0",
          "red_original" : "1",
          "red" : "150",
          "green_original" : "1",
          "green" : "40",
          "blue_original" : "1",
          "blue" : "-255"
        }
      }
    },
    "f12" : {
      "start" : {
        "x" : "0",
        "y" : "0",
        "rotation" : "0",
        "scaleX" : "1.05",
        "scaleY" : "0.87",
        "color" : {
          "alpha_original" : "1",
          "alpha" : "0",
          "red_original" : "1",
          "red" : "150",
          "green_original" : "1",
          "green" : "40",
          "blue_original" : "1",
          "blue" : "-255"
        }
      },
      "nextFrame" : "f15",
      "frames" : "4"
    },
    "f15" : {
      "start" : {
        "x" : "-141.8",
        "y" : "-177.2",
        "rotation" : "0",
        "scaleX" : "1.01",
        "scaleY" : "0.99",
        "color" : {
          "alpha_original" : "1",
          "alpha" : "0",
          "red_original" : "1",
          "red" : "109",
          "green_original" : "1",
          "green" : "29",
          "blue_original" : "1",
          "blue" : "-185"
        }
      },
      "nextFrame" : "f19",
      "frames" : "5"
    },
    "f19" : {
      "start" : {
        "x" : "-211.05",
        "y" : "-248.9",
        "rotation" : "0",
        "scaleX" : "1",
        "scaleY" : "1",
        "color" : {
          "alpha_original" : "1",
          "alpha" : "0",
          "red_original" : "1",
          "red" : "150",
          "green_original" : "1",
          "green" : "40",
          "blue_original" : "1",
          "blue" : "-255"
        }
      },
      "nextFrame" : "f22",
      "frames" : "4"
    },
    "f22" : {
      "start" : {
        "x" : "-239.05",
        "y" : "-270.9",
        "rotation" : "0",
        "scaleX" : "1",
        "scaleY" : "1",
        "color" : {
          "alpha_original" : "0",
          "alpha" : "0",
          "red_original" : "1",
          "red" : "150",
          "green_original" : "1",
          "green" : "40",
          "blue_original" : "1",
          "blue" : "-255"
        }
      }
    },
    "f33" : {
      "start" : {
        "x" : "94.75",
        "y" : "-242.85",
        "rotation" : "0",
        "scaleX" : "0.91",
        "scaleY" : "0.91",
        "color" : {
          "alpha_original" : "0",
          "alpha" : "0",
          "red_original" : "1",
          "red" : "150",
          "green_original" : "1",
          "green" : "40",
          "blue_original" : "1",
          "blue" : "-255"
        }
      },
      "nextFrame" : "f36",
      "frames" : "4"
    },
    "f36" : {
      "start" : {
        "x" : "0",
        "y" : "0",
        "rotation" : "0",
        "scaleX" : "1",
        "scaleY" : "1",
        "color" : {
          "alpha_original" : "1",
          "alpha" : "0",
          "red_original" : "1",
          "red" : "0",
          "green_original" : "1",
          "green" : "0",
          "blue_original" : "1",
          "blue" : "0"
        }
      },
      "nextFrame" : "f39",
      "frames" : "4"
    },
    "f39" : {
      "start" : {
        "x" : "0",
        "y" : "0",
        "rotation" : "0",
        "scaleX" : "1.05",
        "scaleY" : "0.93",
        "color" : {
          "alpha_original" : "1",
          "alpha" : "0",
          "red_original" : "1",
          "red" : "0",
          "green_original" : "1",
          "green" : "0",
          "blue_original" : "1",
          "blue" : "0"
        }
      },
      "nextFrame" : "f42",
      "frames" : "4"
    },
    "f42" : {
      "start" : {
        "x" : "0",
        "y" : "0",
        "rotation" : "0",
        "scaleX" : "1",
        "scaleY" : "1",
        "color" : {
          "alpha_original" : "1",
          "alpha" : "0",
          "red_original" : "1",
          "red" : "0",
          "green_original" : "1",
          "green" : "0",
          "blue_original" : "1",
          "blue" : "0"
        }
      }
    }
  },
  "card_layer2" : {
    "f13" : {
      "start" : {
        "x" : "-27.8",
        "y" : "-32.1",
        "rotation" : "0",
        "scaleX" : "1.05",
        "scaleY" : "0.96",
        "color" : {
          "alpha_original" : "0.6",
          "alpha" : "0",
          "red_original" : "1",
          "red" : "150",
          "green_original" : "1",
          "green" : "40",
          "blue_original" : "1",
          "blue" : "-255"
        }
      },
      "nextFrame" : "f15",
      "frames" : "3"
    },
    "f15" : {
      "start" : {
        "x" : "-87.8",
        "y" : "-105.2",
        "rotation" : "0",
        "scaleX" : "1.01",
        "scaleY" : "0.99",
        "color" : {
          "alpha_original" : "0.6",
          "alpha" : "0",
          "red_original" : "1",
          "red" : "109",
          "green_original" : "1",
          "green" : "29",
          "blue_original" : "1",
          "blue" : "-185"
        }
      },
      "nextFrame" : "f19",
      "frames" : "5"
    },
    "f19" : {
      "start" : {
        "x" : "-185.05",
        "y" : "-216.85",
        "rotation" : "0",
        "scaleX" : "1",
        "scaleY" : "1",
        "color" : {
          "alpha_original" : "0.6",
          "alpha" : "0",
          "red_original" : "1",
          "red" : "150",
          "green_original" : "1",
          "green" : "40",
          "blue_original" : "1",
          "blue" : "-255"
        }
      },
      "nextFrame" : "f22",
      "frames" : "4"
    },
    "f22" : {
      "start" : {
        "x" : "-239.05",
        "y" : "-270.9",
        "rotation" : "0",
        "scaleX" : "1",
        "scaleY" : "1",
        "color" : {
          "alpha_original" : "0",
          "alpha" : "0",
          "red_original" : "1",
          "red" : "150",
          "green_original" : "1",
          "green" : "40",
          "blue_original" : "1",
          "blue" : "-255"
        }
      }
    },
    "f33" : {
      "start" : {
        "x" : "94.75",
        "y" : "-242.85",
        "rotation" : "0",
        "scaleX" : "0.91",
        "scaleY" : "0.91",
        "color" : {
          "alpha_original" : "0.6",
          "alpha" : "0",
          "red_original" : "1",
          "red" : "150",
          "green_original" : "1",
          "green" : "40",
          "blue_original" : "1",
          "blue" : "-255"
        }
      },
      "nextFrame" : "f36",
      "frames" : "4"
    },
    "f36" : {
      "start" : {
        "x" : "25.7",
        "y" : "-38",
        "rotation" : "0",
        "scaleX" : "1",
        "scaleY" : "1",
        "color" : {
          "alpha_original" : "0.6",
          "alpha" : "0",
          "red_original" : "1",
          "red" : "0",
          "green_original" : "1",
          "green" : "0",
          "blue_original" : "1",
          "blue" : "0"
        }
      },
      "nextFrame" : "f38",
      "frames" : "3"
    },
    "f38" : {
      "start" : {
        "x" : "0",
        "y" : "0",
        "rotation" : "0",
        "scaleX" : "1",
        "scaleY" : "1",
        "color" : {
          "alpha_original" : "1",
          "alpha" : "0",
          "red_original" : "1",
          "red" : "0",
          "green_original" : "1",
          "green" : "0",
          "blue_original" : "1",
          "blue" : "0"
        }
      }
    },
    "f39" : {
      "remove" : "1"
    }
  },
  "card_layer3" : {
    "f13" : {
      "start" : {
        "x" : "0.15",
        "y" : "-0.15",
        "rotation" : "0",
        "scaleX" : "1.05",
        "scaleY" : "0.96",
        "color" : {
          "alpha_original" : "0.6",
          "alpha" : "0",
          "red_original" : "1",
          "red" : "150",
          "green_original" : "1",
          "green" : "40",
          "blue_original" : "1",
          "blue" : "-255"
        }
      },
      "nextFrame" : "f15",
      "frames" : "3"
    },
    "f15" : {
      "start" : {
        "x" : "-29.8",
        "y" : "-37.15",
        "rotation" : "0",
        "scaleX" : "1.01",
        "scaleY" : "0.99",
        "color" : {
          "alpha_original" : "0.3",
          "alpha" : "0",
          "red_original" : "1",
          "red" : "109",
          "green_original" : "1",
          "green" : "29",
          "blue_original" : "1",
          "blue" : "-185"
        }
      },
      "nextFrame" : "f19",
      "frames" : "5"
    },
    "f19" : {
      "start" : {
        "x" : "-155.45",
        "y" : "-180.6",
        "rotation" : "0",
        "scaleX" : "1",
        "scaleY" : "1",
        "color" : {
          "alpha_original" : "0.3",
          "alpha" : "0",
          "red_original" : "1",
          "red" : "150",
          "green_original" : "1",
          "green" : "40",
          "blue_original" : "1",
          "blue" : "-255"
        }
      },
      "nextFrame" : "f22",
      "frames" : "4"
    },
    "f22" : {
      "start" : {
        "x" : "-239.05",
        "y" : "-270.9",
        "rotation" : "0",
        "scaleX" : "1",
        "scaleY" : "1",
        "color" : {
          "alpha_original" : "0",
          "alpha" : "0",
          "red_original" : "1",
          "red" : "150",
          "green_original" : "1",
          "green" : "40",
          "blue_original" : "1",
          "blue" : "-255"
        }
      }
    },
    "f33" : {
      "start" : {
        "x" : "94.75",
        "y" : "-242.85",
        "rotation" : "0",
        "scaleX" : "0.91",
        "scaleY" : "0.91",
        "color" : {
          "alpha_original" : "0",
          "alpha" : "0",
          "red_original" : "1",
          "red" : "150",
          "green_original" : "1",
          "green" : "40",
          "blue_original" : "1",
          "blue" : "-255"
        }
      },
      "nextFrame" : "f36",
      "frames" : "4"
    },
    "f36" : {
      "start" : {
        "x" : "57.7",
        "y" : "-90.7",
        "rotation" : "0",
        "scaleX" : "1",
        "scaleY" : "1",
        "color" : {
          "alpha_original" : "0.3",
          "alpha" : "0",
          "red_original" : "1",
          "red" : "0",
          "green_original" : "1",
          "green" : "0",
          "blue_original" : "1",
          "blue" : "0"
        }
      },
      "nextFrame" : "f40",
      "frames" : "5"
    },
    "f40" : {
      "start" : {
        "x" : "0",
        "y" : "0",
        "rotation" : "0",
        "scaleX" : "1",
        "scaleY" : "1",
        "color" : {
          "alpha_original" : "1",
          "alpha" : "0",
          "red_original" : "1",
          "red" : "0",
          "green_original" : "1",
          "green" : "0",
          "blue_original" : "1",
          "blue" : "0"
        }
      }
    },
    "f41" : {
      "remove" : "1"
    }
  },
  "base_layer2" : {
    "f13" : {
      "start" : {
        "x" : "-27.8",
        "y" : "-32.1",
        "rotation" : "0",
        "scaleX" : "1.05",
        "scaleY" : "0.96",
        "color" : {
          "alpha_original" : "0.6",
          "alpha" : "0",
          "red_original" : "1",
          "red" : "150",
          "green_original" : "1",
          "green" : "40",
          "blue_original" : "1",
          "blue" : "-255"
        }
      },
      "nextFrame" : "f15",
      "frames" : "3"
    },
    "f15" : {
      "start" : {
        "x" : "-87.8",
        "y" : "-105.2",
        "rotation" : "0",
        "scaleX" : "1.01",
        "scaleY" : "0.99",
        "color" : {
          "alpha_original" : "0.6",
          "alpha" : "0",
          "red_original" : "1",
          "red" : "109",
          "green_original" : "1",
          "green" : "29",
          "blue_original" : "1",
          "blue" : "-185"
        }
      },
      "nextFrame" : "f19",
      "frames" : "5"
    },
    "f19" : {
      "start" : {
        "x" : "-185.05",
        "y" : "-216.85",
        "rotation" : "0",
        "scaleX" : "1",
        "scaleY" : "1",
        "color" : {
          "alpha_original" : "0.6",
          "alpha" : "0",
          "red_original" : "1",
          "red" : "150",
          "green_original" : "1",
          "green" : "40",
          "blue_original" : "1",
          "blue" : "-255"
        }
      },
      "nextFrame" : "f22",
      "frames" : "4"
    },
    "f22" : {
      "start" : {
        "x" : "-239.05",
        "y" : "-270.9",
        "rotation" : "0",
        "scaleX" : "1",
        "scaleY" : "1",
        "color" : {
          "alpha_original" : "0",
          "alpha" : "0",
          "red_original" : "1",
          "red" : "150",
          "green_original" : "1",
          "green" : "40",
          "blue_original" : "1",
          "blue" : "-255"
        }
      }
    },
    "f33" : {
      "start" : {
        "x" : "94.75",
        "y" : "-242.85",
        "rotation" : "0",
        "scaleX" : "0.91",
        "scaleY" : "0.91",
        "color" : {
          "alpha_original" : "0.6",
          "alpha" : "0",
          "red_original" : "1",
          "red" : "150",
          "green_original" : "1",
          "green" : "40",
          "blue_original" : "1",
          "blue" : "-255"
        }
      },
      "nextFrame" : "f36",
      "frames" : "4"
    },
    "f36" : {
      "start" : {
        "x" : "25.7",
        "y" : "-38",
        "rotation" : "0",
        "scaleX" : "1",
        "scaleY" : "1",
        "color" : {
          "alpha_original" : "0.6",
          "alpha" : "0",
          "red_original" : "1",
          "red" : "0",
          "green_original" : "1",
          "green" : "0",
          "blue_original" : "1",
          "blue" : "0"
        }
      },
      "nextFrame" : "f38",
      "frames" : "3"
    },
    "f38" : {
      "start" : {
        "x" : "0",
        "y" : "0",
        "rotation" : "0",
        "scaleX" : "1",
        "scaleY" : "1",
        "color" : {
          "alpha_original" : "1",
          "alpha" : "0",
          "red_original" : "1",
          "red" : "0",
          "green_original" : "1",
          "green" : "0",
          "blue_original" : "1",
          "blue" : "0"
        }
      }
    },
    "f39" : {
      "remove" : "1"
    }
  },
  "base_layer3" : {
    "f13" : {
      "start" : {
        "x" : "0.15",
        "y" : "5.85",
        "rotation" : "0",
        "scaleX" : "1",
        "scaleY" : "1",
        "color" : {
          "alpha_original" : "0.6",
          "alpha" : "0",
          "red_original" : "1",
          "red" : "150",
          "green_original" : "1",
          "green" : "40",
          "blue_original" : "1",
          "blue" : "-255"
        }
      },
      "nextFrame" : "f15",
      "frames" : "3"
    },
    "f15" : {
      "start" : {
        "x" : "-29.8",
        "y" : "-31.15",
        "rotation" : "0",
        "scaleX" : "1",
        "scaleY" : "1",
        "color" : {
          "alpha_original" : "0.3",
          "alpha" : "0",
          "red_original" : "1",
          "red" : "109",
          "green_original" : "1",
          "green" : "29",
          "blue_original" : "1",
          "blue" : "-185"
        }
      },
      "nextFrame" : "f19",
      "frames" : "5"
    },
    "f19" : {
      "start" : {
        "x" : "-155.45",
        "y" : "-174.6",
        "rotation" : "0",
        "scaleX" : "1",
        "scaleY" : "1",
        "color" : {
          "alpha_original" : "0.3",
          "alpha" : "0",
          "red_original" : "1",
          "red" : "150",
          "green_original" : "1",
          "green" : "40",
          "blue_original" : "1",
          "blue" : "-255"
        }
      },
      "nextFrame" : "f22",
      "frames" : "4"
    },
    "f22" : {
      "start" : {
        "x" : "-239.05",
        "y" : "-264.9",
        "rotation" : "0",
        "scaleX" : "1",
        "scaleY" : "1",
        "color" : {
          "alpha_original" : "0",
          "alpha" : "0",
          "red_original" : "1",
          "red" : "150",
          "green_original" : "1",
          "green" : "40",
          "blue_original" : "1",
          "blue" : "-255"
        }
      }
    },
    "f33" : {
      "start" : {
        "x" : "94.75",
        "y" : "-237.35",
        "rotation" : "0",
        "scaleX" : "0.91",
        "scaleY" : "0.91",
        "color" : {
          "alpha_original" : "0",
          "alpha" : "0",
          "red_original" : "1",
          "red" : "150",
          "green_original" : "1",
          "green" : "40",
          "blue_original" : "1",
          "blue" : "-255"
        }
      },
      "nextFrame" : "f36",
      "frames" : "4"
    },
    "f36" : {
      "start" : {
        "x" : "57.7",
        "y" : "-84.7",
        "rotation" : "0",
        "scaleX" : "1",
        "scaleY" : "1",
        "color" : {
          "alpha_original" : "0.3",
          "alpha" : "0",
          "red_original" : "1",
          "red" : "0",
          "green_original" : "1",
          "green" : "0",
          "blue_original" : "1",
          "blue" : "0"
        }
      },
      "nextFrame" : "f40",
      "frames" : "5"
    },
    "f40" : {
      "start" : {
        "x" : "0",
        "y" : "0",
        "rotation" : "0",
        "scaleX" : "1",
        "scaleY" : "1",
        "color" : {
          "alpha_original" : "1",
          "alpha" : "0",
          "red_original" : "1",
          "red" : "0",
          "green_original" : "1",
          "green" : "0",
          "blue_original" : "1",
          "blue" : "0"
        }
      }
    },
    "f41" : {
      "remove" : "1"
    }
  },
  "sp_stage_center_layer" : {

  },
  "sp_up_layer" : {
    "f4" : {
      "start" : {
        "x" : "3.4",
        "y" : "42.25",
        "rotation" : "0",
        "scaleX" : "-1.95",
        "scaleY" : "1.95",
        "color" : {
          "alpha_original" : "1",
          "alpha" : "0",
          "red_original" : "1",
          "red" : "255",
          "green_original" : "1",
          "green" : "0",
          "blue_original" : "1",
          "blue" : "-255"
        }
      }
    },
    "f12" : {
      "remove" : "1"
    },
    "useBatchNode" : "false",
    "spId" : "sp_2group_wslw_start_2"
  },
  "sp_down_layer" : {

  },
  "events" : {
    "f43" : "finish"
  }
}