{
  "base_layer" : {
    "f1" : {
      "start" : {
        "x" : "-5.9",
        "y" : "0",
        "rotation" : "0",
        "scaleX" : "1",
        "scaleY" : "1",
        "opacity" : "255"
      },
      "nextFrame" : "f4",
      "frames" : "4"
    },
    "f4" : {
      "start" : {
        "x" : "-21.95",
        "y" : "0",
        "rotation" : "0",
        "scaleX" : "1",
        "scaleY" : "1",
        "opacity" : "255"
      },
      "nextFrame" : "f7",
      "frames" : "4"
    },
    "f7" : {
      "start" : {
        "x" : "-36.55",
        "y" : "0",
        "rotation" : "0",
        "scaleX" : "1",
        "scaleY" : "1",
        "opacity" : "255"
      },
      "nextFrame" : "f10",
      "frames" : "4"
    },
    "f10" : {
      "start" : {
        "x" : "-51.15",
        "y" : "0",
        "rotation" : "0",
        "scaleX" : "1",
        "scaleY" : "1",
        "opacity" : "255"
      }
    },
    "f20" : {
      "start" : {
        "x" : "-51.15",
        "y" : "0",
        "rotation" : "0",
        "scaleX" : "1",
        "scaleY" : "1",
        "opacity" : "255"
      },
      "nextFrame" : "f24",
      "frames" : "5"
    },
    "f24" : {
      "start" : {
        "x" : "0",
        "y" : "0",
        "rotation" : "0",
        "scaleX" : "1",
        "scaleY" : "1",
        "opacity" : "255"
      }
    }
  },
  "card_layer" : {
    "f1" : {
      "start" : {
        "x" : "-8.05",
        "y" : "0",
        "rotation" : "-11.06",
        "scaleX" : "1",
        "scaleY" : "1",
        "color" : {
          "alpha_original" : "1",
          "alpha" : "0",
          "red_original" : "1",
          "red" : "0",
          "green_original" : "1",
          "green" : "60",
          "blue_original" : "1",
          "blue" : "90"
        }
      },
      "nextFrame" : "f4",
      "frames" : "4"
    },
    "f4" : {
      "start" : {
        "x" : "-21.85",
        "y" : "0",
        "rotation" : "-35.32",
        "scaleX" : "1",
        "scaleY" : "1",
        "color" : {
          "alpha_original" : "1",
          "alpha" : "0",
          "red_original" : "1",
          "red" : "0",
          "green_original" : "1",
          "green" : "60",
          "blue_original" : "1",
          "blue" : "90"
        }
      },
      "nextFrame" : "f7",
      "frames" : "4"
    },
    "f7" : {
      "start" : {
        "x" : "-36.45",
        "y" : "0",
        "rotation" : "7.06",
        "scaleX" : "1",
        "scaleY" : "0.96",
        "color" : {
          "alpha_original" : "1",
          "alpha" : "0",
          "red_original" : "1",
          "red" : "0",
          "green_original" : "1",
          "green" : "60",
          "blue_original" : "1",
          "blue" : "90"
        }
      },
      "nextFrame" : "f10",
      "frames" : "4"
    },
    "f10" : {
      "start" : {
        "x" : "-48.15",
        "y" : "0",
        "rotation" : "-8.56",
        "scaleX" : "1",
        "scaleY" : "1",
        "color" : {
          "alpha_original" : "1",
          "alpha" : "0",
          "red_original" : "1",
          "red" : "0",
          "green_original" : "1",
          "green" : "60",
          "blue_original" : "1",
          "blue" : "90"
        }
      },
      "nextFrame" : "f13",
      "frames" : "4"
    },
    "f13" : {
      "start" : {
        "x" : "-48.15",
        "y" : "0",
        "rotation" : "1.5",
        "scaleX" : "1",
        "scaleY" : "1",
        "color" : {
          "alpha_original" : "1",
          "alpha" : "0",
          "red_original" : "1",
          "red" : "0",
          "green_original" : "1",
          "green" : "60",
          "blue_original" : "1",
          "blue" : "90"
        }
      },
      "nextFrame" : "f15",
      "frames" : "3"
    },
    "f15" : {
      "start" : {
        "x" : "-49.7",
        "y" : "0",
        "rotation" : "0",
        "scaleX" : "1",
        "scaleY" : "1",
        "color" : {
          "alpha_original" : "1",
          "alpha" : "0",
          "red_original" : "1",
          "red" : "0",
          "green_original" : "1",
          "green" : "60",
          "blue_original" : "1",
          "blue" : "90"
        }
      },
      "nextFrame" : "f20",
      "frames" : "6"
    },
    "f20" : {
      "start" : {
        "x" : "-49.7",
        "y" : "0",
        "rotation" : "0",
        "scaleX" : "1",
        "scaleY" : "1",
        "color" : {
          "alpha_original" : "1",
          "alpha" : "0",
          "red_original" : "1",
          "red" : "0",
          "green_original" : "1",
          "green" : "0",
          "blue_original" : "1",
          "blue" : "0"
        }
      },
      "nextFrame" : "f24",
      "frames" : "5"
    },
    "f24" : {
      "start" : {
        "x" : "0",
        "y" : "0",
        "rotation" : "0",
        "scaleX" : "1",
        "scaleY" : "1",
        "color" : {
          "alpha_original" : "1",
          "alpha" : "0",
          "red_original" : "1",
          "red" : "0",
          "green_original" : "1",
          "green" : "0",
          "blue_original" : "1",
          "blue" : "0"
        }
      }
    }
  },
  "sp_stage_center_layer" : {

  },
  "sp_up_layer" : {
    "f1" : {
      "start" : {
        "x" : "4.85",
        "y" : "0",
        "rotation" : "0",
        "scaleX" : "-1",
        "scaleY" : "1",
        "opacity" : "255"
      }
    },
    "useBatchNode" : "true",
    "spId" : "sp_hit_chuizi_dangongxuli"
  },
  "sp_down_layer" : {

  },
  "events" : {
    "f24" : "finish"
  }
}