<?xml version="1.0" encoding="UTF-8"?>
<!-- id=ID type=邮件类型 value=系统分类 -->
<root>
    <data id="1" type="1" value="1" />
    <data id="2" type="1" value="7" />
    <data id="3" type="2" value="7" />
    <data id="4" type="2" value="7" />
    <data id="5" type="2" value="7" />
    <data id="6" type="1" value="3" />
    <data id="7" type="2" value="7" />
    <data id="8" type="1" value="3" />
    <data id="9" type="1" value="3" />
    <data id="10" type="1" value="3" />
    <data id="11" type="1" value="3" />
    <data id="12" type="2" value="7" />
    <data id="13" type="2" value="7" />
    <data id="14" type="1" value="6" />
    <data id="15" type="1" value="6" />
    <data id="16" type="2" value="7" />
    <data id="17" type="1" value="2" />
    <data id="18" type="1" value="2" />
    <data id="19" type="1" value="2" />
    <data id="20" type="1" value="4" />
    <data id="21" type="1" value="4" />
    <data id="22" type="1" value="4" />
    <data id="23" type="1" value="4" />
    <data id="24" type="2" value="4" />
    <data id="25" type="1" value="4" />
    <data id="26" type="1" value="4" />
    <data id="27" type="1" value="4" />
    <data id="28" type="1" value="4" />
    <data id="29" type="1" value="6" />
    <data id="30" type="2" value="7" />
    <data id="31" type="2" value="4" />
    <data id="32" type="2" value="7" />
    <data id="33" type="2" value="7" />
    <data id="34" type="2" value="7" />
    <data id="35" type="2" value="7" />
    <data id="36" type="2" value="7" />
    <data id="37" type="2" value="7" />
    <data id="38" type="2" value="7" />
    <data id="39" type="2" value="7" />
    <data id="40" type="2" value="7" />
    <data id="41" type="2" value="7" />
    <data id="42" type="2" value="7" />
    <data id="43" type="2" value="7" />
    <data id="44" type="2" value="7" />
    <data id="45" type="2" value="7" />
    <data id="46" type="2" value="7" />
    <data id="47" type="2" value="7" />
    <data id="48" type="2" value="7" />
    <data id="49" type="2" value="7" />
    <data id="50" type="2" value="7" />
    <data id="51" type="1" value="2" />
    <data id="52" type="1" value="2" />
    <data id="53" type="1" value="6" />
    <data id="54" type="2" value="7" />
    <data id="55" type="2" value="7" />
    <data id="56" type="2" value="7" />
    <data id="57" type="2" value="7" />
    <data id="58" type="2" value="7" />
    <data id="59" type="2" value="7" />
    <data id="60" type="2" value="6" />
    <data id="61" type="2" value="7" />
    <data id="62" type="1" value="3" />
    <data id="63" type="1" value="4" />
</root>